Workbook

Sheet Base_Clientes
A1: ID_Cliente | B1: Nome_Cliente | C1: Cidade | D1: UF | E1: Idade | F1: Segmento | G1: Canal_Aquisicao | H1: Plano_ID | I1: Nome_Plano_PROCX | J1: Valor_Plano_PROCV | K1: Data_Entrada | L1: Mes_Entrada | M1: Status | N1: Data_Cancelamento | O1: Tempo_Cliente_Dias | P1: Faixa_Tempo_Cliente | Q1: Churn | R1: NPS | S1: Receita_Perdida | T1: Classificacao_NPS | U1: Risco_Churn | V1: Atrasos_Pagamento | W1: Uso_30d | X1: Mensalidade_Paga | Y1: Tempo_Cliente_Meses | Z1: Risco_Churn2
A2: C0001 | B2: Valentina Souza | C2: São Paulo | D2: SP | E2: 65 | F2: Pessoa Física | G2: LinkedIn | H2: P001 | I2: =_xludf.XLOOKUP(H2,Base_Planos!$A:$A,Base_Planos!$B:$B,"Não encontrado") -> #NAME? | J2: =VLOOKUP(H2,Base_Planos!$A:$G,4,FALSE) -> 39.9 | K2: 45136 | L2: 2023-07 | M2: Cancelado | N2: 45261 | O2: =IF(M2="Cancelado",N2-K2,TODAY()-K2) -> 125 | P2: =IF(O2<=30,"Até 30 dias",IF(O2<=90,"31 a 90 dias",IF(O2<=180,"91 a 180 dias",IF(O2<=365,"181 a 365 dias","Mais de 1 ano")))) -> 91 a 180 dias | Q2: =IF(M2="Cancelado",1,0) -> 1 | R2: 10 | S2: =IF(Q2=1,J2,0) -> 39.9 | T2: =IF(R2<=6,"Detrator",IF(R2<=8,"Neutro","Promotor")) -> Promotor | U2: =IF(Q2=1,"Alto risco",IF(R2<=6,"Alto risco",IF(R2<=8,"Médio risco","Baixo risco"))) -> Alto risco | V2: 1 | W2: 21 | X2: 35.77 | Y2: 4 | Z2: Médio
A3: C0002 | B3: Thiago Silva | C3: Goiânia | D3: GO | E3: 30 | F3: Pequena Empresa | G3: Parceiro | H3: P002 | I3: =_xludf.XLOOKUP(H3,Base_Planos!$A:$A,Base_Planos!$B:$B,"Não encontrado") -> #NAME? | J3: =VLOOKUP(H3,Base_Planos!$A:$G,4,FALSE) -> 29.9 | K3: 46133 | L3: 2026-04 | M3: Ativo | O3: =IF(M3="Cancelado",N3-K3,TODAY()-K3) -> 36 | P3: =IF(O3<=30,"Até 30 dias",IF(O3<=90,"31 a 90 dias",IF(O3<=180,"91 a 180 dias",IF(O3<=365,"181 a 365 dias","Mais de 1 ano")))) -> 31 a 90 dias | Q3: =IF(M3="Cancelado",1,0) -> 0 | R3: 4 | S3: =IF(Q3=1,J3,0) -> 0 | T3: =IF(R3<=6,"Detrator",IF(R3<=8,"Neutro","Promotor")) -> Detrator | U3: =IF(Q3=1,"Alto risco",IF(R3<=6,"Alto risco",IF(R3<=8,"Médio risco","Baixo risco"))) -> Alto risco | V3: 2 | W3: 54 | X3: 27.45 | Y3: 1 | Z3: Alto
A4: C0003 | B4: Eduarda Costa | C4: Santo André | D4: SP | E4: 39 | F4: Pessoa Física | G4: Parceiro | H4: P001 | I4: =_xludf.XLOOKUP(H4,Base_Planos!$A:$A,Base_Planos!$B:$B,"Não encontrado") -> #NAME? | J4: =VLOOKUP(H4,Base_Planos!$A:$G,4,FALSE) -> 39.9 | K4: 45631 | L4: 2024-12 | M4: Cancelado | N4: 46133 | O4: =IF(M4="Cancelado",N4-K4,TODAY()-K4) -> 502 | P4: =IF(O4<=30,"Até 30 dias",IF(O4<=90,"31 a 90 dias",IF(O4<=180,"91 a 180 dias",IF(O4<=365,"181 a 365 dias","Mais de 1 ano")))) -> Mais de 1 ano | Q4: =IF(M4="Cancelado",1,0) -> 1 | R4: 9 | S4: =IF(Q4=1,J4,0) -> 39.9 | T4: =IF(R4<=6,"Detrator",IF(R4<=8,"Neutro","Promotor")) -> Promotor | U4: =IF(Q4=1,"Alto risco",IF(R4<=6,"Alto risco",IF(R4<=8,"Médio risco","Baixo risco"))) -> Alto risco | V4: 0 | W4: 65 | X4: 34.54 | Y4: 16 | Z4: Baixo
A5: C0004 | B5: João Nascimento | C5: Guarulhos | D5: SP | E5: 41 | F5: MEI | G5: Instagram | H5: P001 | I5: =_xludf.XLOOKUP(H5,Base_Planos!$A:$A,Base_Planos!$B:$B,"Não encontrado") -> #NAME? | J5: =VLOOKUP(H5,Base_Planos!$A:$G,4,FALSE) -> 39.9 | K5: 45393 | L5: 2024-04 | M5: Cancelado | N5: 45887 | O5: =IF(M5="Cancelado",N5-K5,TODAY()-K5) -> 494 | P5: =IF(O5<=30,"Até 30 dias",IF(O5<=90,"31 a 90 dias",IF(O5<=180,"91 a 180 dias",IF(O5<=365,"181 a 365 dias","Mais de 1 ano")))) -> Mais de 1 ano | Q5: =IF(M5="Cancelado",1,0) -> 1 | R5: 4 | S5: =IF(Q5=1,J5,0) -> 39.9 | T5: =IF(R5<=6,"Detrator",IF(R5<=8,"Neutro","Promotor")) -> Detrator | U5: =IF(Q5=1,"Alto risco",IF(R5<=6,"Alto risco",IF(R5<=8,"Médio risco","Baixo risco"))) -> Alto risco | V5: 2 | W5: 51 | X5: 36.83 | Y5: 16 | Z5: Alto
A6: C0005 | B6: Lucas Martins | C6: Curitiba | D6: PR | E6: 60 | F6: Pessoa Física | G6: Instagram | H6: P004 | I6: =_xludf.XLOOKUP(H6,Base_Planos!$A:$A,Base_Planos!$B:$B,"Não encontrado") -> #NAME? | J6: =VLOOKUP(H6,Base_Planos!$A:$G,4,FALSE) -> 59.9 | K6: 45277 | L6: 2023-12 | M6: Ativo | O6: =IF(M6="Cancelado",N6-K6,TODAY()-K6) -> 892 | P6: =IF(O6<=30,"Até 30 dias",IF(O6<=90,"31 a 90 dias",IF(O6<=180,"91 a 180 dias",IF(O6<=365,"181 a 365 dias","Mais de 1 ano")))) -> Mais de 1 ano | Q6: =IF(M6="Cancelado",1,0) -> 0 | R6: 8 | S6: =IF(Q6=1,J6,0) -> 0 | T6: =IF(R6<=6,"Detrator",IF(R6<=8,"Neutro","Promotor")) -> Neutro | U6: =IF(Q6=1,"Alto risco",IF(R6<=6,"Alto risco",IF(R6<=8,"Médio risco","Baixo risco"))) -> Médio risco | V6: 0 | W6: 40 | X6: 58.58 | Y6: 29 | Z6: Baixo
A7: C0006 | B7: Rafael Ferreira | C7: Osasco | D7: SP | E7: 38 | F7: Média Empresa | G7: Google Ads | H7: P002 | I7: =_xludf.XLOOKUP(H7,Base_Planos!$A:$A,Base_Planos!$B:$B,"Não encontrado") -> #NAME? | J7: =VLOOKUP(H7,Base_Planos!$A:$G,4,FALSE) -> 29.9 | K7: 44992 | L7: 2023-03 | M7: Ativo | O7: =IF(M7="Cancelado",N7-K7,TODAY()-K7) -> 1177 | P7: =IF(O7<=30,"Até 30 dias",IF(O7<=90,"31 a 90 dias",IF(O7<=180,"91 a 180 dias",IF(O7<=365,"181 a 365 dias","Mais de 1 ano")))) -> Mais de 1 ano | Q7: =IF(M7="Cancelado",1,0) -> 0 | R7: 5 | S7: =IF(Q7=1,J7,0) -> 0 | T7: =IF(R7<=6,"Detrator",IF(R7<=8,"Neutro","Promotor")) -> Detrator | U7: =IF(Q7=1,"Alto risco",IF(R7<=6,"Alto risco",IF(R7<=8,"Médio risco","Baixo risco"))) -> Alto risco | V7: 3 | W7: 63 | X7: 29.71 | Y7: 39 | Z7: Médio
A8: C0007 | B8: Gabriela Barbosa | C8: Salvador | D8: BA | E8: 59 | F8: MEI | G8: Orgânico | H8: P001 | I8: =_xludf.XLOOKUP(H8,Base_Planos!$A:$A,Base_Planos!$B:$B,"Não encontrado") -> #NAME? | J8: =VLOOKUP(H8,Base_Planos!$A:$G,4,FALSE) -> 39.9 | K8: 46076 | L8: 2026-02 | M8: Ativo | O8: =IF(M8="Cancelado",N8-K8,TODAY()-K8) -> 93 | P8: =IF(O8<=30,"Até 30 dias",IF(O8<=90,"31 a 90 dias",IF(O8<=180,"91 a 180 dias",IF(O8<=365,"181 a 365 dias","Mais de 1 ano")))) -> 91 a 180 dias | Q8: =IF(M8="Cancelado",1,0) -> 0 | R8: 8 | S8: =IF(Q8=1,J8,0) -> 0 | T8: =IF(R8<=6,"Detrator",IF(R8<=8,"Neutro","Promotor")) -> Neutro | U8: =IF(Q8=1,"Alto risco",IF(R8<=6,"Alto risco",IF(R8<=8,"Médio risco","Baixo risco"))) -> Médio risco | V8: 2 | W8: 93 | X8: 35.67 | Y8: 3 | Z8: Baixo
A9: C0008 | B9: Eduarda Rocha | C9: Fortaleza | D9: CE | E9: 23 | F9: Pequena Empresa | G9: Instagram | H9: P001 | I9: =_xludf.XLOOKUP(H9,Base_Planos!$A:$A,Base_Planos!$B:$B,"Não encontrado") -> #NAME? | J9: =VLOOKUP(H9,Base_Planos!$A:$G,4,FALSE) -> 39.9 | K9: 45254 | L9: 2023-11 | M9: Ativo | O9: =IF(M9="Cancelado",N9-K9,TODAY()-K9) -> 915 | P9: =IF(O9<=30,"Até 30 dias",IF(O9<=90,"31 a 90 dias",IF(O9<=180,"91 a 180 dias",IF(O9<=365,"181 a 365 dias","Mais de 1 ano")))) -> Mais de 1 ano | Q9: =IF(M9="Cancelado",1,0) -> 0 | R9: 10 | S9: =IF(Q9=1,J9,0) -> 0 | T9: =IF(R9<=6,"Detrator",IF(R9<=8,"Neutro","Promotor")) -> Promotor | U9: =IF(Q9=1,"Alto risco",IF(R9<=6,"Alto risco",IF(R9<=8,"Médio risco","Baixo risco"))) -> Baixo risco | V9: 0 | W9: 61 | X9: 38.14 | Y9: 30 | Z9: Baixo
A10: C0009 | B10: Rafael Silva | C10: Osasco | D10: SP | E10: 64 | F10: Pessoa Física | G10: Orgânico | H10: P005 | I10: =_xludf.XLOOKUP(H10,Base_Planos!$A:$A,Base_Planos!$B:$B,"Não encontrado") -> #NAME? | J10: =VLOOKUP(H10,Base_Planos!$A:$G,4,FALSE) -> 149.9 | K10: 45623 | L10: 2024-11 | M10: Ativo | O10: =IF(M10="Cancelado",N10-K10,TODAY()-K10) -> 546 | P10: =IF(O10<=30,"Até 30 dias",IF(O10<=90,"31 a 90 dias",IF(O10<=180,"91 a 180 dias",IF(O10<=365,"181 a 365 dias","Mais de 1 ano")))) -> Mais de 1 ano | Q10: =IF(M10="Cancelado",1,0) -> 0 | R10: 1 | S10: =IF(Q10=1,J10,0) -> 0 | T10: =IF(R10<=6,"Detrator",IF(R10<=8,"Neutro","Promotor")) -> Detrator | U10: =IF(Q10=1,"Alto risco",IF(R10<=6,"Alto risco",IF(R10<=8,"Médio risco","Baixo risco"))) -> Alto risco | V10: 0 | W10: 72 | X10: 148.99 | Y10: 18 | Z10: Médio
A11: C0010 | B11: Queila Lima | C11: Goiânia | D11: GO | E11: 24 | F11: Média Empresa | G11: Orgânico | H11: P006 | I11: =_xludf.XLOOKUP(H11,Base_Planos!$A:$A,Base_Planos!$B:$B,"Não encontrado") -> #NAME? | J11: =VLOOKUP(H11,Base_Planos!$A:$G,4,FALSE) -> 119.9 | K11: 45966 | L11: 2025-11 | M11: Ativo | O11: =IF(M11="Cancelado",N11-K11,TODAY()-K11) -> 203 | P11: =IF(O11<=30,"Até 30 dias",IF(O11<=90,"31 a 90 dias",IF(O11<=180,"91 a 180 dias",IF(O11<=365,"181 a 365 dias","Mais de 1 ano")))) -> 181 a 365 dias | Q11: =IF(M11="Cancelado",1,0) -> 0 | R11: 9 | S11: =IF(Q11=1,J11,0) -> 0 | T11: =IF(R11<=6,"Detrator",IF(R11<=8,"Neutro","Promotor")) -> Promotor | U11: =IF(Q11=1,"Alto risco",IF(R11<=6,"Alto risco",IF(R11<=8,"Médio risco","Baixo risco"))) -> Baixo risco | V11: 0 | W11: 82 | X11: 124.03 | Y11: 6 | Z11: Baixo
A12: C0011 | B12: Gustavo Silva | C12: Campinas | D12: SP | E12: 38 | F12: MEI | G12: Instagram | H12: P006 | I12: =_xludf.XLOOKUP(H12,Base_Planos!$A:$A,Base_Planos!$B:$B,"Não encontrado") -> #NAME? | J12: =VLOOKUP(H12,Base_Planos!$A:$G,4,FALSE) -> 119.9 | K12: 45556 | L12: 2024-09 | M12: Cancelado | N12: 46083 | O12: =IF(M12="Cancelado",N12-K12,TODAY()-K12) -> 527 | P12: =IF(O12<=30,"Até 30 dias",IF(O12<=90,"31 a 90 dias",IF(O12<=180,"91 a 180 dias",IF(O12<=365,"181 a 365 dias","Mais de 1 ano")))) -> Mais de 1 ano | Q12: =IF(M12="Cancelado",1,0) -> 1 | R12: 3 | S12: =IF(Q12=1,J12,0) -> 119.9 | T12: =IF(R12<=6,"Detrator",IF(R12<=8,"Neutro","Promotor")) -> Detrator | U12: =IF(Q12=1,"Alto risco",IF(R12<=6,"Alto risco",IF(R12<=8,"Médio risco","Baixo risco"))) -> Alto risco | V12: 3 | W12: 77 | X12: 125.37 | Y12: 17 | Z12: Alto
A13: C0012 | B13: Rafael Pereira | C13: Belo Horizonte | D13: MG | E13: 60 | F13: MEI | G13: Indicação | H13: P002 | I13: =_xludf.XLOOKUP(H13,Base_Planos!$A:$A,Base_Planos!$B:$B,"Não encontrado") -> #NAME? | J13: =VLOOKUP(H13,Base_Planos!$A:$G,4,FALSE) -> 29.9 | K13: 45793 | L13: 2025-05 | M13: Ativo | O13: =IF(M13="Cancelado",N13-K13,TODAY()-K13) -> 376 | P13: =IF(O13<=30,"Até 30 dias",IF(O13<=90,"31 a 90 dias",IF(O13<=180,"91 a 180 dias",IF(O13<=365,"181 a 365 dias","Mais de 1 ano")))) -> Mais de 1 ano | Q13: =IF(M13="Cancelado",1,0) -> 0 | R13: 3 | S13: =IF(Q13=1,J13,0) -> 0 | T13: =IF(R13<=6,"Detrator",IF(R13<=8,"Neutro","Promotor")) -> Detrator | U13: =IF(Q13=1,"Alto risco",IF(R13<=6,"Alto risco",IF(R13<=8,"Médio risco","Baixo risco"))) -> Alto risco | V13: 1 | W13: 36 | X13: 27.8 | Y13: 12 | Z13: Alto
A14: C0013 | B14: Wesley Martins | C14: Fortaleza | D14: CE | E14: 51 | F14: MEI | G14: LinkedIn | H14: P002 | I14: =_xludf.XLOOKUP(H14,Base_Planos!$A:$A,Base_Planos!$B:$B,"Não encontrado") -> #NAME? | J14: =VLOOKUP(H14,Base_Planos!$A:$G,4,FALSE) -> 29.9 | K14: 45619 | L14: 2024-11 | M14: Cancelado | N14: 45709 | O14: =IF(M14="Cancelado",N14-K14,TODAY()-K14) -> 90 | P14: =IF(O14<=30,"Até 30 dias",IF(O14<=90,"31 a 90 dias",IF(O14<=180,"91 a 180 dias",IF(O14<=365,"181 a 365 dias","Mais de 1 ano")))) -> 31 a 90 dias | Q14: =IF(M14="Cancelado",1,0) -> 1 | R14: 0 | S14: =IF(Q14=1,J14,0) -> 29.9 | T14: =IF(R14<=6,"Detrator",IF(R14<=8,"Neutro","Promotor")) -> Detrator | U14: =IF(Q14=1,"Alto risco",IF(R14<=6,"Alto risco",IF(R14<=8,"Médio risco","Baixo risco"))) -> Alto risco | V14: 0 | W14: 46 | X14: 30.83 | Y14: 3 | Z14: Médio
A15: C0014 | B15: Enzo Ribeiro | C15: Rio de Janeiro | D15: RJ | E15: 50 | F15: Pessoa Física | G15: E-mail marketing | H15: P002 | I15: =_xludf.XLOOKUP(H15,Base_Planos!$A:$A,Base_Planos!$B:$B,"Não encontrado") -> #NAME? | J15: =VLOOKUP(H15,Base_Planos!$A:$G,4,FALSE) -> 29.9 | K15: 45197 | L15: 2023-09 | M15: Ativo | O15: =IF(M15="Cancelado",N15-K15,TODAY()-K15) -> 972 | P15: =IF(O15<=30,"Até 30 dias",IF(O15<=90,"31 a 90 dias",IF(O15<=180,"91 a 180 dias",IF(O15<=365,"181 a 365 dias","Mais de 1 ano")))) -> Mais de 1 ano | Q15: =IF(M15="Cancelado",1,0) -> 0 | R15: 9 | S15: =IF(Q15=1,J15,0) -> 0 | T15: =IF(R15<=6,"Detrator",IF(R15<=8,"Neutro","Promotor")) -> Promotor | U15: =IF(Q15=1,"Alto risco",IF(R15<=6,"Alto risco",IF(R15<=8,"Médio risco","Baixo risco"))) -> Baixo risco | V15: 0 | W15: 47 | X15: 25.98 | Y15: 32 | Z15: Baixo
A16: C0015 | B16: Wesley Araújo | C16: Recife | D16: PE | E16: 45 | F16: MEI | G16: Google Ads | H16: P004 | I16: =_xludf.XLOOKUP(H16,Base_Planos!$A:$A,Base_Planos!$B:$B,"Não encontrado") -> #NAME? | J16: =VLOOKUP(H16,Base_Planos!$A:$G,4,FALSE) -> 59.9 | K16: 45128 | L16: 2023-07 | M16: Cancelado | N16: 45352 | O16: =IF(M16="Cancelado",N16-K16,TODAY()-K16) -> 224 | P16: =IF(O16<=30,"Até 30 dias",IF(O16<=90,"31 a 90 dias",IF(O16<=180,"91 a 180 dias",IF(O16<=365,"181 a 365 dias","Mais de 1 ano")))) -> 181 a 365 dias | Q16: =IF(M16="Cancelado",1,0) -> 1 | R16: 0 | S16: =IF(Q16=1,J16,0) -> 59.9 | T16: =IF(R16<=6,"Detrator",IF(R16<=8,"Neutro","Promotor")) -> Detrator | U16: =IF(Q16=1,"Alto risco",IF(R16<=6,"Alto risco",IF(R16<=8,"Médio risco","Baixo risco"))) -> Alto risco | V16: 2 | W16: 71 | X16: 52.59 | Y16: 7 | Z16: Médio
A17: C0016 | B17: Felipe Almeida | C17: Fortaleza | D17: CE | E17: 33 | F17: Média Empresa | G17: Instagram | H17: P003 | I17: =_xludf.XLOOKUP(H17,Base_Planos!$A:$A,Base_Planos!$B:$B,"Não encontrado") -> #NAME? | J17: =VLOOKUP(H17,Base_Planos!$A:$G,4,FALSE) -> 79.9 | K17: 46054 | L17: 2026-02 | M17: Ativo | O17: =IF(M17="Cancelado",N17-K17,TODAY()-K17) -> 115 | P17: =IF(O17<=30,"Até 30 dias",IF(O17<=90,"31 a 90 dias",IF(O17<=180,"91 a 180 dias",IF(O17<=365,"181 a 365 dias","Mais de 1 ano")))) -> 91 a 180 dias | Q17: =IF(M17="Cancelado",1,0) -> 0 | R17: 1 | S17: =IF(Q17=1,J17,0) -> 0 | T17: =IF(R17<=6,"Detrator",IF(R17<=8,"Neutro","Promotor")) -> Detrator | U17: =IF(Q17=1,"Alto risco",IF(R17<=6,"Alto risco",IF(R17<=8,"Médio risco","Baixo risco"))) -> Alto risco | V17: 2 | W17: 90 | X17: 82.72 | Y17: 3 | Z17: Alto
A18: C0017 | B18: Enzo Ferreira | C18: Belo Horizonte | D18: MG | E18: 44 | F18: MEI | G18: LinkedIn | H18: P006 | I18: =_xludf.XLOOKUP(H18,Base_Planos!$A:$A,Base_Planos!$B:$B,"Não encontrado") -> #NAME? | J18: =VLOOKUP(H18,Base_Planos!$A:$G,4,FALSE) -> 119.9 | K18: 45047 | L18: 2023-05 | M18: Ativo | O18: =IF(M18="Cancelado",N18-K18,TODAY()-K18) -> 1122 | P18: =IF(O18<=30,"Até 30 dias",IF(O18<=90,"31 a 90 dias",IF(O18<=180,"91 a 180 dias",IF(O18<=365,"181 a 365 dias","Mais de 1 ano")))) -> Mais de 1 ano | Q18: =IF(M18="Cancelado",1,0) -> 0 | R18: 2 | S18: =IF(Q18=1,J18,0) -> 0 | T18: =IF(R18<=6,"Detrator",IF(R18<=8,"Neutro","Promotor")) -> Detrator | U18: =IF(Q18=1,"Alto risco",IF(R18<=6,"Alto risco",IF(R18<=8,"Médio risco","Baixo risco"))) -> Alto risco | V18: 0 | W18: 100 | X18: 112.83 | Y18: 37 | Z18: Médio
A19: C0018 | B19: Nicolas Dias | C19: Osasco | D19: SP | E19: 63 | F19: MEI | G19: LinkedIn | H19: P002 | I19: =_xludf.XLOOKUP(H19,Base_Planos!$A:$A,Base_Planos!$B:$B,"Não encontrado") -> #NAME? | J19: =VLOOKUP(H19,Base_Planos!$A:$G,4,FALSE) -> 29.9 | K19: 45046 | L19: 2023-04 | M19: Cancelado | N19: 46052 | O19: =IF(M19="Cancelado",N19-K19,TODAY()-K19) -> 1006 | P19: =IF(O19<=30,"Até 30 dias",IF(O19<=90,"31 a 90 dias",IF(O19<=180,"91 a 180 dias",IF(O19<=365,"181 a 365 dias","Mais de 1 ano")))) -> Mais de 1 ano | Q19: =IF(M19="Cancelado",1,0) -> 1 | R19: 9 | S19: =IF(Q19=1,J19,0) -> 29.9 | T19: =IF(R19<=6,"Detrator",IF(R19<=8,"Neutro","Promotor")) -> Promotor | U19: =IF(Q19=1,"Alto risco",IF(R19<=6,"Alto risco",IF(R19<=8,"Médio risco","Baixo risco"))) -> Alto risco | V19: 0 | W19: 47 | X19: 25.76 | Y19: 33 | Z19: Baixo
A20: C0019 | B20: Queila Oliveira | C20: Guarulhos | D20: SP | E20: 29 | F20: Pessoa Física | G20: Instagram | H20: P004 | I20: =_xludf.XLOOKUP(H20,Base_Planos!$A:$A,Base_Planos!$B:$B,"Não encontrado") -> #NAME? | J20: =VLOOKUP(H20,Base_Planos!$A:$G,4,FALSE) -> 59.9 | K20: 45408 | L20: 2024-04 | M20: Ativo | O20: =IF(M20="Cancelado",N20-K20,TODAY()-K20) -> 761 | P20: =IF(O20<=30,"Até 30 dias",IF(O20<=90,"31 a 90 dias",IF(O20<=180,"91 a 180 dias",IF(O20<=365,"181 a 365 dias","Mais de 1 ano")))) -> Mais de 1 ano | Q20: =IF(M20="Cancelado",1,0) -> 0 | R20: 6 | S20: =IF(Q20=1,J20,0) -> 0 | T20: =IF(R20<=6,"Detrator",IF(R20<=8,"Neutro","Promotor")) -> Detrator | U20: =IF(Q20=1,"Alto risco",IF(R20<=6,"Alto risco",IF(R20<=8,"Médio risco","Baixo risco"))) -> Alto risco | V20: 0 | W20: 97 | X20: 58.34 | Y20: 25 | Z20: Médio
A21: C0020 | B21: Nicolas Teixeira | C21: Campinas | D21: SP | E21: 51 | F21: Pessoa Física | G21: Orgânico | H21: P002 | I21: =_xludf.XLOOKUP(H21,Base_Planos!$A:$A,Base_Planos!$B:$B,"Não encontrado") -> #NAME? | J21: =VLOOKUP(H21,Base_Planos!$A:$G,4,FALSE) -> 29.9 | K21: 45570 | L21: 2024-10 | M21: Ativo | O21: =IF(M21="Cancelado",N21-K21,TODAY()-K21) -> 599 | P21: =IF(O21<=30,"Até 30 dias",IF(O21<=90,"31 a 90 dias",IF(O21<=180,"91 a 180 dias",IF(O21<=365,"181 a 365 dias","Mais de 1 ano")))) -> Mais de 1 ano | Q21: =IF(M21="Cancelado",1,0) -> 0 | R21: 3 | S21: =IF(Q21=1,J21,0) -> 0 | T21: =IF(R21<=6,"Detrator",IF(R21<=8,"Neutro","Promotor")) -> Detrator | U21: =IF(Q21=1,"Alto risco",IF(R21<=6,"Alto risco",IF(R21<=8,"Médio risco","Baixo risco"))) -> Alto risco | V21: 1 | W21: 71 | X21: 30.97 | Y21: 19 | Z21: Médio
A22: C0021 | B22: Gustavo Oliveira | C22: São Paulo | D22: SP | E22: 47 | F22: Pequena Empresa | G22: Instagram | H22: P001 | I22: =_xludf.XLOOKUP(H22,Base_Planos!$A:$A,Base_Planos!$B:$B,"Não encontrado") -> #NAME? | J22: =VLOOKUP(H22,Base_Planos!$A:$G,4,FALSE) -> 39.9 | K22: 45363 | L22: 2024-03 | M22: Ativo | O22: =IF(M22="Cancelado",N22-K22,TODAY()-K22) -> 806 | P22: =IF(O22<=30,"Até 30 dias",IF(O22<=90,"31 a 90 dias",IF(O22<=180,"91 a 180 dias",IF(O22<=365,"181 a 365 dias","Mais de 1 ano")))) -> Mais de 1 ano | Q22: =IF(M22="Cancelado",1,0) -> 0 | R22: 8 | S22: =IF(Q22=1,J22,0) -> 0 | T22: =IF(R22<=6,"Detrator",IF(R22<=8,"Neutro","Promotor")) -> Neutro | U22: =IF(Q22=1,"Alto risco",IF(R22<=6,"Alto risco",IF(R22<=8,"Médio risco","Baixo risco"))) -> Médio risco | V22: 2 | W22: 100 | X22: 36.86 | Y22: 26 | Z22: Baixo
A23: C0022 | B23: Felipe Melo | C23: Guarulhos | D23: SP | E23: 52 | F23: Pequena Empresa | G23: Google Ads | H23: P004 | I23: =_xludf.XLOOKUP(H23,Base_Planos!$A:$A,Base_Planos!$B:$B,"Não encontrado") -> #NAME? | J23: =VLOOKUP(H23,Base_Planos!$A:$G,4,FALSE) -> 59.9 | K23: 46062 | L23: 2026-02 | M23: Cancelado | N23: 46105 | O23: =IF(M23="Cancelado",N23-K23,TODAY()-K23) -> 43 | P23: =IF(O23<=30,"Até 30 dias",IF(O23<=90,"31 a 90 dias",IF(O23<=180,"91 a 180 dias",IF(O23<=365,"181 a 365 dias","Mais de 1 ano")))) -> 31 a 90 dias | Q23: =IF(M23="Cancelado",1,0) -> 1 | R23: 4 | S23: =IF(Q23=1,J23,0) -> 59.9 | T23: =IF(R23<=6,"Detrator",IF(R23<=8,"Neutro","Promotor")) -> Detrator | U23: =IF(Q23=1,"Alto risco",IF(R23<=6,"Alto risco",IF(R23<=8,"Médio risco","Baixo risco"))) -> Alto risco | V23: 2 | W23: 51 | X23: 52.78 | Y23: 1 | Z23: Alto
A24: C0023 | B24: João Nascimento | C24: Curitiba | D24: PR | E24: 63 | F24: Pessoa Física | G24: Orgânico | H24: P003 | I24: =_xludf.XLOOKUP(H24,Base_Planos!$A:$A,Base_Planos!$B:$B,"Não encontrado") -> #NAME? | J24: =VLOOKUP(H24,Base_Planos!$A:$G,4,FALSE) -> 79.9 | K24: 45441 | L24: 2024-05 | M24: Cancelado | N24: 45604 | O24: =IF(M24="Cancelado",N24-K24,TODAY()-K24) -> 163 | P24: =IF(O24<=30,"Até 30 dias",IF(O24<=90,"31 a 90 dias",IF(O24<=180,"91 a 180 dias",IF(O24<=365,"181 a 365 dias","Mais de 1 ano")))) -> 91 a 180 dias | Q24: =IF(M24="Cancelado",1,0) -> 1 | R24: 0 | S24: =IF(Q24=1,J24,0) -> 79.9 | T24: =IF(R24<=6,"Detrator",IF(R24<=8,"Neutro","Promotor")) -> Detrator | U24: =IF(Q24=1,"Alto risco",IF(R24<=6,"Alto risco",IF(R24<=8,"Médio risco","Baixo risco"))) -> Alto risco | V24: 0 | W24: 73 | X24: 72.1 | Y24: 5 | Z24: Médio
A25: C0024 | B25: Zeca Melo | C25: Goiânia | D25: GO | E25: 63 | F25: MEI | G25: Google Ads | H25: P001 | I25: =_xludf.XLOOKUP(H25,Base_Planos!$A:$A,Base_Planos!$B:$B,"Não encontrado") -> #NAME? | J25: =VLOOKUP(H25,Base_Planos!$A:$G,4,FALSE) -> 39.9 | K25: 45232 | L25: 2023-11 | M25: Ativo | O25: =IF(M25="Cancelado",N25-K25,TODAY()-K25) -> 937 | P25: =IF(O25<=30,"Até 30 dias",IF(O25<=90,"31 a 90 dias",IF(O25<=180,"91 a 180 dias",IF(O25<=365,"181 a 365 dias","Mais de 1 ano")))) -> Mais de 1 ano | Q25: =IF(M25="Cancelado",1,0) -> 0 | R25: 8 | S25: =IF(Q25=1,J25,0) -> 0 | T25: =IF(R25<=6,"Detrator",IF(R25<=8,"Neutro","Promotor")) -> Neutro | U25: =IF(Q25=1,"Alto risco",IF(R25<=6,"Alto risco",IF(R25<=8,"Médio risco","Baixo risco"))) -> Médio risco | V25: 0 | W25: 63 | X25: 34.25 | Y25: 31 | Z25: Baixo
A26: C0025 | B26: Lucas Santos | C26: Recife | D26: PE | E26: 31 | F26: Pequena Empresa | G26: Instagram | H26: P003 | I26: =_xludf.XLOOKUP(H26,Base_Planos!$A:$A,Base_Planos!$B:$B,"Não encontrado") -> #NAME? | J26: =VLOOKUP(H26,Base_Planos!$A:$G,4,FALSE) -> 79.9 | K26: 46073 | L26: 2026-02 | M26: Cancelado | N26: 46123 | O26: =IF(M26="Cancelado",N26-K26,TODAY()-K26) -> 50 | P26: =IF(O26<=30,"Até 30 dias",IF(O26<=90,"31 a 90 dias",IF(O26<=180,"91 a 180 dias",IF(O26<=365,"181 a 365 dias","Mais de 1 ano")))) -> 31 a 90 dias | Q26: =IF(M26="Cancelado",1,0) -> 1 | R26: 6 | S26: =IF(Q26=1,J26,0) -> 79.9 | T26: =IF(R26<=6,"Detrator",IF(R26<=8,"Neutro","Promotor")) -> Detrator | U26: =IF(Q26=1,"Alto risco",IF(R26<=6,"Alto risco",IF(R26<=8,"Médio risco","Baixo risco"))) -> Alto risco | V26: 3 | W26: 49 | X26: 82 | Y26: 1 | Z26: Alto
A27: C0026 | B27: Ana Lima | C27: Barueri | D27: SP | E27: 39 | F27: Pequena Empresa | G27: Parceiro | H27: P005 | I27: =_xludf.XLOOKUP(H27,Base_Planos!$A:$A,Base_Planos!$B:$B,"Não encontrado") -> #NAME? | J27: =VLOOKUP(H27,Base_Planos!$A:$G,4,FALSE) -> 149.9 | K27: 45435 | L27: 2024-05 | M27: Cancelado | N27: 45946 | O27: =IF(M27="Cancelado",N27-K27,TODAY()-K27) -> 511 | P27: =IF(O27<=30,"Até 30 dias",IF(O27<=90,"31 a 90 dias",IF(O27<=180,"91 a 180 dias",IF(O27<=365,"181 a 365 dias","Mais de 1 ano")))) -> Mais de 1 ano | Q27: =IF(M27="Cancelado",1,0) -> 1 | R27: 4 | S27: =IF(Q27=1,J27,0) -> 149.9 | T27: =IF(R27<=6,"Detrator",IF(R27<=8,"Neutro","Promotor")) -> Detrator | U27: =IF(Q27=1,"Alto risco",IF(R27<=6,"Alto risco",IF(R27<=8,"Médio risco","Baixo risco"))) -> Alto risco | V27: 0 | W27: 93 | X27: 151.9 | Y27: 17 | Z27: Médio
A28: C0027 | B28: Olívia Martins | C28: Porto Alegre | D28: RS | E28: 32 | F28: Pessoa Física | G28: LinkedIn | H28: P003 | I28: =_xludf.XLOOKUP(H28,Base_Planos!$A:$A,Base_Planos!$B:$B,"Não encontrado") -> #NAME? | J28: =VLOOKUP(H28,Base_Planos!$A:$G,4,FALSE) -> 79.9 | K28: 45497 | L28: 2024-07 | M28: Ativo | O28: =IF(M28="Cancelado",N28-K28,TODAY()-K28) -> 672 | P28: =IF(O28<=30,"Até 30 dias",IF(O28<=90,"31 a 90 dias",IF(O28<=180,"91 a 180 dias",IF(O28<=365,"181 a 365 dias","Mais de 1 ano")))) -> Mais de 1 ano | Q28: =IF(M28="Cancelado",1,0) -> 0 | R28: 1 | S28: =IF(Q28=1,J28,0) -> 0 | T28: =IF(R28<=6,"Detrator",IF(R28<=8,"Neutro","Promotor")) -> Detrator | U28: =IF(Q28=1,"Alto risco",IF(R28<=6,"Alto risco",IF(R28<=8,"Médio risco","Baixo risco"))) -> Alto risco | V28: 1 | W28: 52 | X28: 83.59 | Y28: 22 | Z28: Médio
A29: C0028 | B29: Rafael Ribeiro | C29: São Paulo | D29: SP | E29: 25 | F29: Média Empresa | G29: Orgânico | H29: P001 | I29: =_xludf.XLOOKUP(H29,Base_Planos!$A:$A,Base_Planos!$B:$B,"Não encontrado") -> #NAME? | J29: =VLOOKUP(H29,Base_Planos!$A:$G,4,FALSE) -> 39.9 | K29: 45470 | L29: 2024-06 | M29: Cancelado | N29: 46120 | O29: =IF(M29="Cancelado",N29-K29,TODAY()-K29) -> 650 | P29: =IF(O29<=30,"Até 30 dias",IF(O29<=90,"31 a 90 dias",IF(O29<=180,"91 a 180 dias",IF(O29<=365,"181 a 365 dias","Mais de 1 ano")))) -> Mais de 1 ano | Q29: =IF(M29="Cancelado",1,0) -> 1 | R29: 0 | S29: =IF(Q29=1,J29,0) -> 39.9 | T29: =IF(R29<=6,"Detrator",IF(R29<=8,"Neutro","Promotor")) -> Detrator | U29: =IF(Q29=1,"Alto risco",IF(R29<=6,"Alto risco",IF(R29<=8,"Médio risco","Baixo risco"))) -> Alto risco | V29: 1 | W29: 75 | X29: 34.84 | Y29: 21 | Z29: Médio
A30: C0029 | B30: Fernanda Teixeira | C30: Curitiba | D30: PR | E30: 34 | F30: Pessoa Física | G30: Parceiro | H30: P001 | I30: =_xludf.XLOOKUP(H30,Base_Planos!$A:$A,Base_Planos!$B:$B,"Não encontrado") -> #NAME? | J30: =VLOOKUP(H30,Base_Planos!$A:$G,4,FALSE) -> 39.9 | K30: 46029 | L30: 2026-01 | M30: Ativo | O30: =IF(M30="Cancelado",N30-K30,TODAY()-K30) -> 140 | P30: =IF(O30<=30,"Até 30 dias",IF(O30<=90,"31 a 90 dias",IF(O30<=180,"91 a 180 dias",IF(O30<=365,"181 a 365 dias","Mais de 1 ano")))) -> 91 a 180 dias | Q30: =IF(M30="Cancelado",1,0) -> 0 | R30: 10 | S30: =IF(Q30=1,J30,0) -> 0 | T30: =IF(R30<=6,"Detrator",IF(R30<=8,"Neutro","Promotor")) -> Promotor | U30: =IF(Q30=1,"Alto risco",IF(R30<=6,"Alto risco",IF(R30<=8,"Médio risco","Baixo risco"))) -> Baixo risco | V30: 1 | W30: 11 | X30: 34.47 | Y30: 4 | Z30: Médio
A31: C0030 | B31: Wesley Ribeiro | C31: Campinas | D31: SP | E31: 38 | F31: Pequena Empresa | G31: Instagram | H31: P005 | I31: =_xludf.XLOOKUP(H31,Base_Planos!$A:$A,Base_Planos!$B:$B,"Não encontrado") -> #NAME? | J31: =VLOOKUP(H31,Base_Planos!$A:$G,4,FALSE) -> 149.9 | K31: 45542 | L31: 2024-09 | M31: Ativo | O31: =IF(M31="Cancelado",N31-K31,TODAY()-K31) -> 627 | P31: =IF(O31<=30,"Até 30 dias",IF(O31<=90,"31 a 90 dias",IF(O31<=180,"91 a 180 dias",IF(O31<=365,"181 a 365 dias","Mais de 1 ano")))) -> Mais de 1 ano | Q31: =IF(M31="Cancelado",1,0) -> 0 | R31: 8 | S31: =IF(Q31=1,J31,0) -> 0 | T31: =IF(R31<=6,"Detrator",IF(R31<=8,"Neutro","Promotor")) -> Neutro | U31: =IF(Q31=1,"Alto risco",IF(R31<=6,"Alto risco",IF(R31<=8,"Médio risco","Baixo risco"))) -> Médio risco | V31: 0 | W31: 83 | X31: 131.23 | Y31: 20 | Z31: Baixo
A32: C0031 | B32: Nicolas Carvalho | C32: Osasco | D32: SP | E32: 65 | F32: Média Empresa | G32: Orgânico | H32: P003 | I32: =_xludf.XLOOKUP(H32,Base_Planos!$A:$A,Base_Planos!$B:$B,"Não encontrado") -> #NAME? | J32: =VLOOKUP(H32,Base_Planos!$A:$G,4,FALSE) -> 79.9 | K32: 44927 | L32: 2023-01 | M32: Ativo | O32: =IF(M32="Cancelado",N32-K32,TODAY()-K32) -> 1242 | P32: =IF(O32<=30,"Até 30 dias",IF(O32<=90,"31 a 90 dias",IF(O32<=180,"91 a 180 dias",IF(O32<=365,"181 a 365 dias","Mais de 1 ano")))) -> Mais de 1 ano | Q32: =IF(M32="Cancelado",1,0) -> 0 | R32: 4 | S32: =IF(Q32=1,J32,0) -> 0 | T32: =IF(R32<=6,"Detrator",IF(R32<=8,"Neutro","Promotor")) -> Detrator | U32: =IF(Q32=1,"Alto risco",IF(R32<=6,"Alto risco",IF(R32<=8,"Médio risco","Baixo risco"))) -> Alto risco | V32: 0 | W32: 85 | X32: 75.35 | Y32: 41 | Z32: Médio
A33: C0032 | B33: Olívia Costa | C33: Goiânia | D33: GO | E33: 48 | F33: Pequena Empresa | G33: Indicação | H33: P004 | I33: =_xludf.XLOOKUP(H33,Base_Planos!$A:$A,Base_Planos!$B:$B,"Não encontrado") -> #NAME? | J33: =VLOOKUP(H33,Base_Planos!$A:$G,4,FALSE) -> 59.9 | K33: 45508 | L33: 2024-08 | M33: Ativo | O33: =IF(M33="Cancelado",N33-K33,TODAY()-K33) -> 661 | P33: =IF(O33<=30,"Até 30 dias",IF(O33<=90,"31 a 90 dias",IF(O33<=180,"91 a 180 dias",IF(O33<=365,"181 a 365 dias","Mais de 1 ano")))) -> Mais de 1 ano | Q33: =IF(M33="Cancelado",1,0) -> 0 | R33: 8 | S33: =IF(Q33=1,J33,0) -> 0 | T33: =IF(R33<=6,"Detrator",IF(R33<=8,"Neutro","Promotor")) -> Neutro | U33: =IF(Q33=1,"Alto risco",IF(R33<=6,"Alto risco",IF(R33<=8,"Médio risco","Baixo risco"))) -> Médio risco | V33: 0 | W33: 23 | X33: 53.73 | Y33: 22 | Z33: Baixo
A34: C0033 | B34: João Ferreira | C34: Santo André | D34: SP | E34: 30 | F34: Pessoa Física | G34: Google Ads | H34: P002 | I34: =_xludf.XLOOKUP(H34,Base_Planos!$A:$A,Base_Planos!$B:$B,"Não encontrado") -> #NAME? | J34: =VLOOKUP(H34,Base_Planos!$A:$G,4,FALSE) -> 29.9 | K34: 45900 | L34: 2025-08 | M34: Ativo | O34: =IF(M34="Cancelado",N34-K34,TODAY()-K34) -> 269 | P34: =IF(O34<=30,"Até 30 dias",IF(O34<=90,"31 a 90 dias",IF(O34<=180,"91 a 180 dias",IF(O34<=365,"181 a 365 dias","Mais de 1 ano")))) -> 181 a 365 dias | Q34: =IF(M34="Cancelado",1,0) -> 0 | R34: 9 | S34: =IF(Q34=1,J34,0) -> 0 | T34: =IF(R34<=6,"Detrator",IF(R34<=8,"Neutro","Promotor")) -> Promotor | U34: =IF(Q34=1,"Alto risco",IF(R34<=6,"Alto risco",IF(R34<=8,"Médio risco","Baixo risco"))) -> Baixo risco | V34: 0 | W34: 48 | X34: 26.58 | Y34: 8 | Z34: Baixo
A35: C0034 | B35: Yasmin Carvalho | C35: Fortaleza | D35: CE | E35: 43 | F35: Pessoa Física | G35: Google Ads | H35: P006 | I35: =_xludf.XLOOKUP(H35,Base_Planos!$A:$A,Base_Planos!$B:$B,"Não encontrado") -> #NAME? | J35: =VLOOKUP(H35,Base_Planos!$A:$G,4,FALSE) -> 119.9 | K35: 45145 | L35: 2023-08 | M35: Ativo | O35: =IF(M35="Cancelado",N35-K35,TODAY()-K35) -> 1024 | P35: =IF(O35<=30,"Até 30 dias",IF(O35<=90,"31 a 90 dias",IF(O35<=180,"91 a 180 dias",IF(O35<=365,"181 a 365 dias","Mais de 1 ano")))) -> Mais de 1 ano | Q35: =IF(M35="Cancelado",1,0) -> 0 | R35: 6 | S35: =IF(Q35=1,J35,0) -> 0 | T35: =IF(R35<=6,"Detrator",IF(R35<=8,"Neutro","Promotor")) -> Detrator | U35: =IF(Q35=1,"Alto risco",IF(R35<=6,"Alto risco",IF(R35<=8,"Médio risco","Baixo risco"))) -> Alto risco | V35: 1 | W35: 100 | X35: 115.28 | Y35: 34 | Z35: Médio
A36: C0035 | B36: Gustavo Souza | C36: Fortaleza | D36: CE | E36: 26 | F36: Pequena Empresa | G36: YouTube | H36: P007 | I36: =_xludf.XLOOKUP(H36,Base_Planos!$A:$A,Base_Planos!$B:$B,"Não encontrado") -> #NAME? | J36: =VLOOKUP(H36,Base_Planos!$A:$G,4,FALSE) -> 399.9 | K36: 45833 | L36: 2025-06 | M36: Ativo | O36: =IF(M36="Cancelado",N36-K36,TODAY()-K36) -> 336 | P36: =IF(O36<=30,"Até 30 dias",IF(O36<=90,"31 a 90 dias",IF(O36<=180,"91 a 180 dias",IF(O36<=365,"181 a 365 dias","Mais de 1 ano")))) -> 181 a 365 dias | Q36: =IF(M36="Cancelado",1,0) -> 0 | R36: 9 | S36: =IF(Q36=1,J36,0) -> 0 | T36: =IF(R36<=6,"Detrator",IF(R36<=8,"Neutro","Promotor")) -> Promotor | U36: =IF(Q36=1,"Alto risco",IF(R36<=6,"Alto risco",IF(R36<=8,"Médio risco","Baixo risco"))) -> Baixo risco | V36: 0 | W36: 2 | X36: 375.58 | Y36: 11 | Z36: Médio
A37: C0036 | B37: Felipe Barbosa | C37: Fortaleza | D37: CE | E37: 34 | F37: Pequena Empresa | G37: Orgânico | H37: P005 | I37: =_xludf.XLOOKUP(H37,Base_Planos!$A:$A,Base_Planos!$B:$B,"Não encontrado") -> #NAME? | J37: =VLOOKUP(H37,Base_Planos!$A:$G,4,FALSE) -> 149.9 | K37: 45994 | L37: 2025-12 | M37: Ativo | O37: =IF(M37="Cancelado",N37-K37,TODAY()-K37) -> 175 | P37: =IF(O37<=30,"Até 30 dias",IF(O37<=90,"31 a 90 dias",IF(O37<=180,"91 a 180 dias",IF(O37<=365,"181 a 365 dias","Mais de 1 ano")))) -> 91 a 180 dias | Q37: =IF(M37="Cancelado",1,0) -> 0 | R37: 7 | S37: =IF(Q37=1,J37,0) -> 0 | T37: =IF(R37<=6,"Detrator",IF(R37<=8,"Neutro","Promotor")) -> Neutro | U37: =IF(Q37=1,"Alto risco",IF(R37<=6,"Alto risco",IF(R37<=8,"Médio risco","Baixo risco"))) -> Médio risco | V37: 0 | W37: 40 | X37: 135.56 | Y37: 5 | Z37: Baixo
A38: C0037 | B38: Karina Dias | C38: Rio de Janeiro | D38: RJ | E38: 26 | F38: Pessoa Física | G38: Parceiro | H38: P004 | I38: =_xludf.XLOOKUP(H38,Base_Planos!$A:$A,Base_Planos!$B:$B,"Não encontrado") -> #NAME? | J38: =VLOOKUP(H38,Base_Planos!$A:$G,4,FALSE) -> 59.9 | K38: 45365 | L38: 2024-03 | M38: Cancelado | N38: 45825 | O38: =IF(M38="Cancelado",N38-K38,TODAY()-K38) -> 460 | P38: =IF(O38<=30,"Até 30 dias",IF(O38<=90,"31 a 90 dias",IF(O38<=180,"91 a 180 dias",IF(O38<=365,"181 a 365 dias","Mais de 1 ano")))) -> Mais de 1 ano | Q38: =IF(M38="Cancelado",1,0) -> 1 | R38: 1 | S38: =IF(Q38=1,J38,0) -> 59.9 | T38: =IF(R38<=6,"Detrator",IF(R38<=8,"Neutro","Promotor")) -> Detrator | U38: =IF(Q38=1,"Alto risco",IF(R38<=6,"Alto risco",IF(R38<=8,"Médio risco","Baixo risco"))) -> Alto risco | V38: 0 | W38: 69 | X38: 60.14 | Y38: 15 | Z38: Médio
A39: C0038 | B39: Yasmin Silva | C39: Guarulhos | D39: SP | E39: 54 | F39: MEI | G39: Google Ads | H39: P007 | I39: =_xludf.XLOOKUP(H39,Base_Planos!$A:$A,Base_Planos!$B:$B,"Não encontrado") -> #NAME? | J39: =VLOOKUP(H39,Base_Planos!$A:$G,4,FALSE) -> 399.9 | K39: 45538 | L39: 2024-09 | M39: Ativo | O39: =IF(M39="Cancelado",N39-K39,TODAY()-K39) -> 631 | P39: =IF(O39<=30,"Até 30 dias",IF(O39<=90,"31 a 90 dias",IF(O39<=180,"91 a 180 dias",IF(O39<=365,"181 a 365 dias","Mais de 1 ano")))) -> Mais de 1 ano | Q39: =IF(M39="Cancelado",1,0) -> 0 | R39: 6 | S39: =IF(Q39=1,J39,0) -> 0 | T39: =IF(R39<=6,"Detrator",IF(R39<=8,"Neutro","Promotor")) -> Detrator | U39: =IF(Q39=1,"Alto risco",IF(R39<=6,"Alto risco",IF(R39<=8,"Médio risco","Baixo risco"))) -> Alto risco | V39: 0 | W39: 1 | X39: 383.59 | Y39: 21 | Z39: Alto
A40: C0039 | B40: Thiago Ferreira | C40: Fortaleza | D40: CE | E40: 32 | F40: Pessoa Física | G40: E-mail marketing | H40: P001 | I40: =_xludf.XLOOKUP(H40,Base_Planos!$A:$A,Base_Planos!$B:$B,"Não encontrado") -> #NAME? | J40: =VLOOKUP(H40,Base_Planos!$A:$G,4,FALSE) -> 39.9 | K40: 45615 | L40: 2024-11 | M40: Ativo | O40: =IF(M40="Cancelado",N40-K40,TODAY()-K40) -> 554 | P40: =IF(O40<=30,"Até 30 dias",IF(O40<=90,"31 a 90 dias",IF(O40<=180,"91 a 180 dias",IF(O40<=365,"181 a 365 dias","Mais de 1 ano")))) -> Mais de 1 ano | Q40: =IF(M40="Cancelado",1,0) -> 0 | R40: 10 | S40: =IF(Q40=1,J40,0) -> 0 | T40: =IF(R40<=6,"Detrator",IF(R40<=8,"Neutro","Promotor")) -> Promotor | U40: =IF(Q40=1,"Alto risco",IF(R40<=6,"Alto risco",IF(R40<=8,"Médio risco","Baixo risco"))) -> Baixo risco | V40: 0 | W40: 31 | X40: 34.93 | Y40: 18 | Z40: Baixo
A41: C0040 | B41: Thiago Dias | C41: São Paulo | D41: SP | E41: 43 | F41: MEI | G41: Google Ads | H41: P001 | I41: =_xludf.XLOOKUP(H41,Base_Planos!$A:$A,Base_Planos!$B:$B,"Não encontrado") -> #NAME? | J41: =VLOOKUP(H41,Base_Planos!$A:$G,4,FALSE) -> 39.9 | K41: 45804 | L41: 2025-05 | M41: Cancelado | N41: 46066 | O41: =IF(M41="Cancelado",N41-K41,TODAY()-K41) -> 262 | P41: =IF(O41<=30,"Até 30 dias",IF(O41<=90,"31 a 90 dias",IF(O41<=180,"91 a 180 dias",IF(O41<=365,"181 a 365 dias","Mais de 1 ano")))) -> 181 a 365 dias | Q41: =IF(M41="Cancelado",1,0) -> 1 | R41: 2 | S41: =IF(Q41=1,J41,0) -> 39.9 | T41: =IF(R41<=6,"Detrator",IF(R41<=8,"Neutro","Promotor")) -> Detrator | U41: =IF(Q41=1,"Alto risco",IF(R41<=6,"Alto risco",IF(R41<=8,"Médio risco","Baixo risco"))) -> Alto risco | V41: 0 | W41: 43 | X41: 39.99 | Y41: 8 | Z41: Alto
A42: C0041 | B42: Marina Almeida | C42: Santo André | D42: SP | E42: 44 | F42: Pessoa Física | G42: Instagram | H42: P003 | I42: =_xludf.XLOOKUP(H42,Base_Planos!$A:$A,Base_Planos!$B:$B,"Não encontrado") -> #NAME? | J42: =VLOOKUP(H42,Base_Planos!$A:$G,4,FALSE) -> 79.9 | K42: 46031 | L42: 2026-01 | M42: Ativo | O42: =IF(M42="Cancelado",N42-K42,TODAY()-K42) -> 138 | P42: =IF(O42<=30,"Até 30 dias",IF(O42<=90,"31 a 90 dias",IF(O42<=180,"91 a 180 dias",IF(O42<=365,"181 a 365 dias","Mais de 1 ano")))) -> 91 a 180 dias | Q42: =IF(M42="Cancelado",1,0) -> 0 | R42: 0 | S42: =IF(Q42=1,J42,0) -> 0 | T42: =IF(R42<=6,"Detrator",IF(R42<=8,"Neutro","Promotor")) -> Detrator | U42: =IF(Q42=1,"Alto risco",IF(R42<=6,"Alto risco",IF(R42<=8,"Médio risco","Baixo risco"))) -> Alto risco | V42: 1 | W42: 56 | X42: 78.33 | Y42: 4 | Z42: Médio
A43: C0042 | B43: Bianca Silva | C43: Curitiba | D43: PR | E43: 30 | F43: Média Empresa | G43: Indicação | H43: P002 | I43: =_xludf.XLOOKUP(H43,Base_Planos!$A:$A,Base_Planos!$B:$B,"Não encontrado") -> #NAME? | J43: =VLOOKUP(H43,Base_Planos!$A:$G,4,FALSE) -> 29.9 | K43: 45896 | L43: 2025-08 | M43: Ativo | O43: =IF(M43="Cancelado",N43-K43,TODAY()-K43) -> 273 | P43: =IF(O43<=30,"Até 30 dias",IF(O43<=90,"31 a 90 dias",IF(O43<=180,"91 a 180 dias",IF(O43<=365,"181 a 365 dias","Mais de 1 ano")))) -> 181 a 365 dias | Q43: =IF(M43="Cancelado",1,0) -> 0 | R43: 10 | S43: =IF(Q43=1,J43,0) -> 0 | T43: =IF(R43<=6,"Detrator",IF(R43<=8,"Neutro","Promotor")) -> Promotor | U43: =IF(Q43=1,"Alto risco",IF(R43<=6,"Alto risco",IF(R43<=8,"Médio risco","Baixo risco"))) -> Baixo risco | V43: 0 | W43: 100 | X43: 27.62 | Y43: 9 | Z43: Baixo
A44: C0043 | B44: Thiago Nascimento | C44: Barueri | D44: SP | E44: 63 | F44: Pessoa Física | G44: Indicação | H44: P007 | I44: =_xludf.XLOOKUP(H44,Base_Planos!$A:$A,Base_Planos!$B:$B,"Não encontrado") -> #NAME? | J44: =VLOOKUP(H44,Base_Planos!$A:$G,4,FALSE) -> 399.9 | K44: 45148 | L44: 2023-08 | M44: Ativo | O44: =IF(M44="Cancelado",N44-K44,TODAY()-K44) -> 1021 | P44: =IF(O44<=30,"Até 30 dias",IF(O44<=90,"31 a 90 dias",IF(O44<=180,"91 a 180 dias",IF(O44<=365,"181 a 365 dias","Mais de 1 ano")))) -> Mais de 1 ano | Q44: =IF(M44="Cancelado",1,0) -> 0 | R44: 9 | S44: =IF(Q44=1,J44,0) -> 0 | T44: =IF(R44<=6,"Detrator",IF(R44<=8,"Neutro","Promotor")) -> Promotor | U44: =IF(Q44=1,"Alto risco",IF(R44<=6,"Alto risco",IF(R44<=8,"Médio risco","Baixo risco"))) -> Baixo risco | V44: 1 | W44: 60 | X44: 371.64 | Y44: 34 | Z44: Baixo
A45: C0044 | B45: Yasmin Costa | C45: Rio de Janeiro | D45: RJ | E45: 55 | F45: Pequena Empresa | G45: LinkedIn | H45: P001 | I45: =_xludf.XLOOKUP(H45,Base_Planos!$A:$A,Base_Planos!$B:$B,"Não encontrado") -> #NAME? | J45: =VLOOKUP(H45,Base_Planos!$A:$G,4,FALSE) -> 39.9 | K45: 45544 | L45: 2024-09 | M45: Ativo | O45: =IF(M45="Cancelado",N45-K45,TODAY()-K45) -> 625 | P45: =IF(O45<=30,"Até 30 dias",IF(O45<=90,"31 a 90 dias",IF(O45<=180,"91 a 180 dias",IF(O45<=365,"181 a 365 dias","Mais de 1 ano")))) -> Mais de 1 ano | Q45: =IF(M45="Cancelado",1,0) -> 0 | R45: 10 | S45: =IF(Q45=1,J45,0) -> 0 | T45: =IF(R45<=6,"Detrator",IF(R45<=8,"Neutro","Promotor")) -> Promotor | U45: =IF(Q45=1,"Alto risco",IF(R45<=6,"Alto risco",IF(R45<=8,"Médio risco","Baixo risco"))) -> Baixo risco | V45: 4 | W45: 48 | X45: 36.69 | Y45: 20 | Z45: Baixo
A46: C0045 | B46: Nicolas Martins | C46: Rio de Janeiro | D46: RJ | E46: 50 | F46: Pequena Empresa | G46: Google Ads | H46: P006 | I46: =_xludf.XLOOKUP(H46,Base_Planos!$A:$A,Base_Planos!$B:$B,"Não encontrado") -> #NAME? | J46: =VLOOKUP(H46,Base_Planos!$A:$G,4,FALSE) -> 119.9 | K46: 45930 | L46: 2025-09 | M46: Ativo | O46: =IF(M46="Cancelado",N46-K46,TODAY()-K46) -> 239 | P46: =IF(O46<=30,"Até 30 dias",IF(O46<=90,"31 a 90 dias",IF(O46<=180,"91 a 180 dias",IF(O46<=365,"181 a 365 dias","Mais de 1 ano")))) -> 181 a 365 dias | Q46: =IF(M46="Cancelado",1,0) -> 0 | R46: 1 | S46: =IF(Q46=1,J46,0) -> 0 | T46: =IF(R46<=6,"Detrator",IF(R46<=8,"Neutro","Promotor")) -> Detrator | U46: =IF(Q46=1,"Alto risco",IF(R46<=6,"Alto risco",IF(R46<=8,"Médio risco","Baixo risco"))) -> Alto risco | V46: 2 | W46: 67 | X46: 105.58 | Y46: 7 | Z46: Médio
A47: C0046 | B47: Felipe Rocha | C47: Osasco | D47: SP | E47: 35 | F47: Pequena Empresa | G47: E-mail marketing | H47: P003 | I47: =_xludf.XLOOKUP(H47,Base_Planos!$A:$A,Base_Planos!$B:$B,"Não encontrado") -> #NAME? | J47: =VLOOKUP(H47,Base_Planos!$A:$G,4,FALSE) -> 79.9 | K47: 45476 | L47: 2024-07 | M47: Ativo | O47: =IF(M47="Cancelado",N47-K47,TODAY()-K47) -> 693 | P47: =IF(O47<=30,"Até 30 dias",IF(O47<=90,"31 a 90 dias",IF(O47<=180,"91 a 180 dias",IF(O47<=365,"181 a 365 dias","Mais de 1 ano")))) -> Mais de 1 ano | Q47: =IF(M47="Cancelado",1,0) -> 0 | R47: 5 | S47: =IF(Q47=1,J47,0) -> 0 | T47: =IF(R47<=6,"Detrator",IF(R47<=8,"Neutro","Promotor")) -> Detrator | U47: =IF(Q47=1,"Alto risco",IF(R47<=6,"Alto risco",IF(R47<=8,"Médio risco","Baixo risco"))) -> Alto risco | V47: 0 | W47: 14 | X47: 71.81 | Y47: 23 | Z47: Alto
A48: C0047 | B48: Olívia Teixeira | C48: Campinas | D48: SP | E48: 60 | F48: MEI | G48: Google Ads | H48: P003 | I48: =_xludf.XLOOKUP(H48,Base_Planos!$A:$A,Base_Planos!$B:$B,"Não encontrado") -> #NAME? | J48: =VLOOKUP(H48,Base_Planos!$A:$G,4,FALSE) -> 79.9 | K48: 45592 | L48: 2024-10 | M48: Cancelado | N48: 45904 | O48: =IF(M48="Cancelado",N48-K48,TODAY()-K48) -> 312 | P48: =IF(O48<=30,"Até 30 dias",IF(O48<=90,"31 a 90 dias",IF(O48<=180,"91 a 180 dias",IF(O48<=365,"181 a 365 dias","Mais de 1 ano")))) -> 181 a 365 dias | Q48: =IF(M48="Cancelado",1,0) -> 1 | R48: 2 | S48: =IF(Q48=1,J48,0) -> 79.9 | T48: =IF(R48<=6,"Detrator",IF(R48<=8,"Neutro","Promotor")) -> Detrator | U48: =IF(Q48=1,"Alto risco",IF(R48<=6,"Alto risco",IF(R48<=8,"Médio risco","Baixo risco"))) -> Alto risco | V48: 0 | W48: 59 | X48: 76.17 | Y48: 10 | Z48: Médio
A49: C0048 | B49: Gabriela Oliveira | C49: Curitiba | D49: PR | E49: 64 | F49: MEI | G49: LinkedIn | H49: P004 | I49: =_xludf.XLOOKUP(H49,Base_Planos!$A:$A,Base_Planos!$B:$B,"Não encontrado") -> #NAME? | J49: =VLOOKUP(H49,Base_Planos!$A:$G,4,FALSE) -> 59.9 | K49: 45932 | L49: 2025-10 | M49: Ativo | O49: =IF(M49="Cancelado",N49-K49,TODAY()-K49) -> 237 | P49: =IF(O49<=30,"Até 30 dias",IF(O49<=90,"31 a 90 dias",IF(O49<=180,"91 a 180 dias",IF(O49<=365,"181 a 365 dias","Mais de 1 ano")))) -> 181 a 365 dias | Q49: =IF(M49="Cancelado",1,0) -> 0 | R49: 7 | S49: =IF(Q49=1,J49,0) -> 0 | T49: =IF(R49<=6,"Detrator",IF(R49<=8,"Neutro","Promotor")) -> Neutro | U49: =IF(Q49=1,"Alto risco",IF(R49<=6,"Alto risco",IF(R49<=8,"Médio risco","Baixo risco"))) -> Médio risco | V49: 0 | W49: 45 | X49: 54.58 | Y49: 7 | Z49: Baixo
A50: C0049 | B50: Sofia Martins | C50: Fortaleza | D50: CE | E50: 53 | F50: MEI | G50: Parceiro | H50: P007 | I50: =_xludf.XLOOKUP(H50,Base_Planos!$A:$A,Base_Planos!$B:$B,"Não encontrado") -> #NAME? | J50: =VLOOKUP(H50,Base_Planos!$A:$G,4,FALSE) -> 399.9 | K50: 46054 | L50: 2026-02 | M50: Ativo | O50: =IF(M50="Cancelado",N50-K50,TODAY()-K50) -> 115 | P50: =IF(O50<=30,"Até 30 dias",IF(O50<=90,"31 a 90 dias",IF(O50<=180,"91 a 180 dias",IF(O50<=365,"181 a 365 dias","Mais de 1 ano")))) -> 91 a 180 dias | Q50: =IF(M50="Cancelado",1,0) -> 0 | R50: 5 | S50: =IF(Q50=1,J50,0) -> 0 | T50: =IF(R50<=6,"Detrator",IF(R50<=8,"Neutro","Promotor")) -> Detrator | U50: =IF(Q50=1,"Alto risco",IF(R50<=6,"Alto risco",IF(R50<=8,"Médio risco","Baixo risco"))) -> Alto risco | V50: 0 | W50: 81 | X50: 397.6 | Y50: 3 | Z50: Baixo
A51: C0050 | B51: Karina Souza | C51: Barueri | D51: SP | E51: 52 | F51: Enterprise | G51: Indicação | H51: P002 | I51: =_xludf.XLOOKUP(H51,Base_Planos!$A:$A,Base_Planos!$B:$B,"Não encontrado") -> #NAME? | J51: =VLOOKUP(H51,Base_Planos!$A:$G,4,FALSE) -> 29.9 | K51: 45918 | L51: 2025-09 | M51: Cancelado | N51: 45973 | O51: =IF(M51="Cancelado",N51-K51,TODAY()-K51) -> 55 | P51: =IF(O51<=30,"Até 30 dias",IF(O51<=90,"31 a 90 dias",IF(O51<=180,"91 a 180 dias",IF(O51<=365,"181 a 365 dias","Mais de 1 ano")))) -> 31 a 90 dias | Q51: =IF(M51="Cancelado",1,0) -> 1 | R51: 4 | S51: =IF(Q51=1,J51,0) -> 29.9 | T51: =IF(R51<=6,"Detrator",IF(R51<=8,"Neutro","Promotor")) -> Detrator | U51: =IF(Q51=1,"Alto risco",IF(R51<=6,"Alto risco",IF(R51<=8,"Médio risco","Baixo risco"))) -> Alto risco | V51: 0 | W51: 0 | X51: 27.19 | Y51: 1 | Z51: Alto
A52: C0051 | B52: Lucas Lima | C52: Porto Alegre | D52: RS | E52: 18 | F52: Pequena Empresa | G52: Indicação | H52: P002 | I52: =_xludf.XLOOKUP(H52,Base_Planos!$A:$A,Base_Planos!$B:$B,"Não encontrado") -> #NAME? | J52: =VLOOKUP(H52,Base_Planos!$A:$G,4,FALSE) -> 29.9 | K52: 45038 | L52: 2023-04 | M52: Ativo | O52: =IF(M52="Cancelado",N52-K52,TODAY()-K52) -> 1131 | P52: =IF(O52<=30,"Até 30 dias",IF(O52<=90,"31 a 90 dias",IF(O52<=180,"91 a 180 dias",IF(O52<=365,"181 a 365 dias","Mais de 1 ano")))) -> Mais de 1 ano | Q52: =IF(M52="Cancelado",1,0) -> 0 | R52: 8 | S52: =IF(Q52=1,J52,0) -> 0 | T52: =IF(R52<=6,"Detrator",IF(R52<=8,"Neutro","Promotor")) -> Neutro | U52: =IF(Q52=1,"Alto risco",IF(R52<=6,"Alto risco",IF(R52<=8,"Médio risco","Baixo risco"))) -> Médio risco | V52: 1 | W52: 100 | X52: 26.03 | Y52: 37 | Z52: Baixo
A53: C0052 | B53: Ana Teixeira | C53: Porto Alegre | D53: RS | E53: 48 | F53: MEI | G53: YouTube | H53: P002 | I53: =_xludf.XLOOKUP(H53,Base_Planos!$A:$A,Base_Planos!$B:$B,"Não encontrado") -> #NAME? | J53: =VLOOKUP(H53,Base_Planos!$A:$G,4,FALSE) -> 29.9 | K53: 45032 | L53: 2023-04 | M53: Cancelado | N53: 45213 | O53: =IF(M53="Cancelado",N53-K53,TODAY()-K53) -> 181 | P53: =IF(O53<=30,"Até 30 dias",IF(O53<=90,"31 a 90 dias",IF(O53<=180,"91 a 180 dias",IF(O53<=365,"181 a 365 dias","Mais de 1 ano")))) -> 181 a 365 dias | Q53: =IF(M53="Cancelado",1,0) -> 1 | R53: 4 | S53: =IF(Q53=1,J53,0) -> 29.9 | T53: =IF(R53<=6,"Detrator",IF(R53<=8,"Neutro","Promotor")) -> Detrator | U53: =IF(Q53=1,"Alto risco",IF(R53<=6,"Alto risco",IF(R53<=8,"Médio risco","Baixo risco"))) -> Alto risco | V53: 2 | W53: 45 | X53: 29.52 | Y53: 6 | Z53: Alto
A54: C0053 | B54: Eduarda Pereira | C54: Santo André | D54: SP | E54: 54 | F54: Média Empresa | G54: Instagram | H54: P007 | I54: =_xludf.XLOOKUP(H54,Base_Planos!$A:$A,Base_Planos!$B:$B,"Não encontrado") -> #NAME? | J54: =VLOOKUP(H54,Base_Planos!$A:$G,4,FALSE) -> 399.9 | K54: 45169 | L54: 2023-08 | M54: Cancelado | N54: 45734 | O54: =IF(M54="Cancelado",N54-K54,TODAY()-K54) -> 565 | P54: =IF(O54<=30,"Até 30 dias",IF(O54<=90,"31 a 90 dias",IF(O54<=180,"91 a 180 dias",IF(O54<=365,"181 a 365 dias","Mais de 1 ano")))) -> Mais de 1 ano | Q54: =IF(M54="Cancelado",1,0) -> 1 | R54: 8 | S54: =IF(Q54=1,J54,0) -> 399.9 | T54: =IF(R54<=6,"Detrator",IF(R54<=8,"Neutro","Promotor")) -> Neutro | U54: =IF(Q54=1,"Alto risco",IF(R54<=6,"Alto risco",IF(R54<=8,"Médio risco","Baixo risco"))) -> Alto risco | V54: 1 | W54: 18 | X54: 412.58 | Y54: 18 | Z54: Médio
A55: C0054 | B55: João Teixeira | C55: Salvador | D55: BA | E55: 37 | F55: MEI | G55: Google Ads | H55: P004 | I55: =_xludf.XLOOKUP(H55,Base_Planos!$A:$A,Base_Planos!$B:$B,"Não encontrado") -> #NAME? | J55: =VLOOKUP(H55,Base_Planos!$A:$G,4,FALSE) -> 59.9 | K55: 45130 | L55: 2023-07 | M55: Cancelado | N55: 45725 | O55: =IF(M55="Cancelado",N55-K55,TODAY()-K55) -> 595 | P55: =IF(O55<=30,"Até 30 dias",IF(O55<=90,"31 a 90 dias",IF(O55<=180,"91 a 180 dias",IF(O55<=365,"181 a 365 dias","Mais de 1 ano")))) -> Mais de 1 ano | Q55: =IF(M55="Cancelado",1,0) -> 1 | R55: 3 | S55: =IF(Q55=1,J55,0) -> 59.9 | T55: =IF(R55<=6,"Detrator",IF(R55<=8,"Neutro","Promotor")) -> Detrator | U55: =IF(Q55=1,"Alto risco",IF(R55<=6,"Alto risco",IF(R55<=8,"Médio risco","Baixo risco"))) -> Alto risco | V55: 0 | W55: 41 | X55: 50.95 | Y55: 19 | Z55: Médio
A56: C0055 | B56: Olívia Nascimento | C56: Fortaleza | D56: CE | E56: 36 | F56: Pessoa Física | G56: Orgânico | H56: P005 | I56: =_xludf.XLOOKUP(H56,Base_Planos!$A:$A,Base_Planos!$B:$B,"Não encontrado") -> #NAME? | J56: =VLOOKUP(H56,Base_Planos!$A:$G,4,FALSE) -> 149.9 | K56: 45856 | L56: 2025-07 | M56: Ativo | O56: =IF(M56="Cancelado",N56-K56,TODAY()-K56) -> 313 | P56: =IF(O56<=30,"Até 30 dias",IF(O56<=90,"31 a 90 dias",IF(O56<=180,"91 a 180 dias",IF(O56<=365,"181 a 365 dias","Mais de 1 ano")))) -> 181 a 365 dias | Q56: =IF(M56="Cancelado",1,0) -> 0 | R56: 1 | S56: =IF(Q56=1,J56,0) -> 0 | T56: =IF(R56<=6,"Detrator",IF(R56<=8,"Neutro","Promotor")) -> Detrator | U56: =IF(Q56=1,"Alto risco",IF(R56<=6,"Alto risco",IF(R56<=8,"Médio risco","Baixo risco"))) -> Alto risco | V56: 1 | W56: 0 | X56: 147.24 | Y56: 10 | Z56: Alto
A57: C0056 | B57: Gustavo Costa | C57: Salvador | D57: BA | E57: 25 | F57: MEI | G57: Indicação | H57: P006 | I57: =_xludf.XLOOKUP(H57,Base_Planos!$A:$A,Base_Planos!$B:$B,"Não encontrado") -> #NAME? | J57: =VLOOKUP(H57,Base_Planos!$A:$G,4,FALSE) -> 119.9 | K57: 45218 | L57: 2023-10 | M57: Ativo | O57: =IF(M57="Cancelado",N57-K57,TODAY()-K57) -> 951 | P57: =IF(O57<=30,"Até 30 dias",IF(O57<=90,"31 a 90 dias",IF(O57<=180,"91 a 180 dias",IF(O57<=365,"181 a 365 dias","Mais de 1 ano")))) -> Mais de 1 ano | Q57: =IF(M57="Cancelado",1,0) -> 0 | R57: 1 | S57: =IF(Q57=1,J57,0) -> 0 | T57: =IF(R57<=6,"Detrator",IF(R57<=8,"Neutro","Promotor")) -> Detrator | U57: =IF(Q57=1,"Alto risco",IF(R57<=6,"Alto risco",IF(R57<=8,"Médio risco","Baixo risco"))) -> Alto risco | V57: 1 | W57: 75 | X57: 124.01 | Y57: 31 | Z57: Alto
A58: C0057 | B58: Olívia Souza | C58: Fortaleza | D58: CE | E58: 62 | F58: Pessoa Física | G58: Parceiro | H58: P007 | I58: =_xludf.XLOOKUP(H58,Base_Planos!$A:$A,Base_Planos!$B:$B,"Não encontrado") -> #NAME? | J58: =VLOOKUP(H58,Base_Planos!$A:$G,4,FALSE) -> 399.9 | K58: 45951 | L58: 2025-10 | M58: Ativo | O58: =IF(M58="Cancelado",N58-K58,TODAY()-K58) -> 218 | P58: =IF(O58<=30,"Até 30 dias",IF(O58<=90,"31 a 90 dias",IF(O58<=180,"91 a 180 dias",IF(O58<=365,"181 a 365 dias","Mais de 1 ano")))) -> 181 a 365 dias | Q58: =IF(M58="Cancelado",1,0) -> 0 | R58: 8 | S58: =IF(Q58=1,J58,0) -> 0 | T58: =IF(R58<=6,"Detrator",IF(R58<=8,"Neutro","Promotor")) -> Neutro | U58: =IF(Q58=1,"Alto risco",IF(R58<=6,"Alto risco",IF(R58<=8,"Médio risco","Baixo risco"))) -> Médio risco | V58: 0 | W58: 57 | X58: 365.69 | Y58: 7 | Z58: Baixo
A59: C0058 | B59: Isabela Silva | C59: Rio de Janeiro | D59: RJ | E59: 32 | F59: Enterprise | G59: Google Ads | H59: P007 | I59: =_xludf.XLOOKUP(H59,Base_Planos!$A:$A,Base_Planos!$B:$B,"Não encontrado") -> #NAME? | J59: =VLOOKUP(H59,Base_Planos!$A:$G,4,FALSE) -> 399.9 | K59: 45478 | L59: 2024-07 | M59: Ativo | O59: =IF(M59="Cancelado",N59-K59,TODAY()-K59) -> 691 | P59: =IF(O59<=30,"Até 30 dias",IF(O59<=90,"31 a 90 dias",IF(O59<=180,"91 a 180 dias",IF(O59<=365,"181 a 365 dias","Mais de 1 ano")))) -> Mais de 1 ano | Q59: =IF(M59="Cancelado",1,0) -> 0 | R59: 9 | S59: =IF(Q59=1,J59,0) -> 0 | T59: =IF(R59<=6,"Detrator",IF(R59<=8,"Neutro","Promotor")) -> Promotor | U59: =IF(Q59=1,"Alto risco",IF(R59<=6,"Alto risco",IF(R59<=8,"Médio risco","Baixo risco"))) -> Baixo risco | V59: 0 | W59: 68 | X59: 413.18 | Y59: 23 | Z59: Baixo
A60: C0059 | B60: Felipe Teixeira | C60: Salvador | D60: BA | E60: 58 | F60: Pequena Empresa | G60: Instagram | H60: P003 | I60: =_xludf.XLOOKUP(H60,Base_Planos!$A:$A,Base_Planos!$B:$B,"Não encontrado") -> #NAME? | J60: =VLOOKUP(H60,Base_Planos!$A:$G,4,FALSE) -> 79.9 | K60: 45763 | L60: 2025-04 | M60: Ativo | O60: =IF(M60="Cancelado",N60-K60,TODAY()-K60) -> 406 | P60: =IF(O60<=30,"Até 30 dias",IF(O60<=90,"31 a 90 dias",IF(O60<=180,"91 a 180 dias",IF(O60<=365,"181 a 365 dias","Mais de 1 ano")))) -> Mais de 1 ano | Q60: =IF(M60="Cancelado",1,0) -> 0 | R60: 5 | S60: =IF(Q60=1,J60,0) -> 0 | T60: =IF(R60<=6,"Detrator",IF(R60<=8,"Neutro","Promotor")) -> Detrator | U60: =IF(Q60=1,"Alto risco",IF(R60<=6,"Alto risco",IF(R60<=8,"Médio risco","Baixo risco"))) -> Alto risco | V60: 0 | W60: 68 | X60: 75.83 | Y60: 13 | Z60: Baixo
A61: C0060 | B61: Wesley Carvalho | C61: Guarulhos | D61: SP | E61: 53 | F61: Pessoa Física | G61: Instagram | H61: P002 | I61: =_xludf.XLOOKUP(H61,Base_Planos!$A:$A,Base_Planos!$B:$B,"Não encontrado") -> #NAME? | J61: =VLOOKUP(H61,Base_Planos!$A:$G,4,FALSE) -> 29.9 | K61: 45589 | L61: 2024-10 | M61: Ativo | O61: =IF(M61="Cancelado",N61-K61,TODAY()-K61) -> 580 | P61: =IF(O61<=30,"Até 30 dias",IF(O61<=90,"31 a 90 dias",IF(O61<=180,"91 a 180 dias",IF(O61<=365,"181 a 365 dias","Mais de 1 ano")))) -> Mais de 1 ano | Q61: =IF(M61="Cancelado",1,0) -> 0 | R61: 1 | S61: =IF(Q61=1,J61,0) -> 0 | T61: =IF(R61<=6,"Detrator",IF(R61<=8,"Neutro","Promotor")) -> Detrator | U61: =IF(Q61=1,"Alto risco",IF(R61<=6,"Alto risco",IF(R61<=8,"Médio risco","Baixo risco"))) -> Alto risco | V61: 0 | W61: 51 | X61: 29.35 | Y61: 19 | Z61: Médio
A62: C0061 | B62: Rafael Melo | C62: Salvador | D62: BA | E62: 21 | F62: Pessoa Física | G62: YouTube | H62: P004 | I62: =_xludf.XLOOKUP(H62,Base_Planos!$A:$A,Base_Planos!$B:$B,"Não encontrado") -> #NAME? | J62: =VLOOKUP(H62,Base_Planos!$A:$G,4,FALSE) -> 59.9 | K62: 45947 | L62: 2025-10 | M62: Ativo | O62: =IF(M62="Cancelado",N62-K62,TODAY()-K62) -> 222 | P62: =IF(O62<=30,"Até 30 dias",IF(O62<=90,"31 a 90 dias",IF(O62<=180,"91 a 180 dias",IF(O62<=365,"181 a 365 dias","Mais de 1 ano")))) -> 181 a 365 dias | Q62: =IF(M62="Cancelado",1,0) -> 0 | R62: 10 | S62: =IF(Q62=1,J62,0) -> 0 | T62: =IF(R62<=6,"Detrator",IF(R62<=8,"Neutro","Promotor")) -> Promotor | U62: =IF(Q62=1,"Alto risco",IF(R62<=6,"Alto risco",IF(R62<=8,"Médio risco","Baixo risco"))) -> Baixo risco | V62: 0 | W62: 60 | X62: 54.37 | Y62: 7 | Z62: Baixo
A63: C0062 | B63: Fernanda Barbosa | C63: Rio de Janeiro | D63: RJ | E63: 19 | F63: Enterprise | G63: LinkedIn | H63: P005 | I63: =_xludf.XLOOKUP(H63,Base_Planos!$A:$A,Base_Planos!$B:$B,"Não encontrado") -> #NAME? | J63: =VLOOKUP(H63,Base_Planos!$A:$G,4,FALSE) -> 149.9 | K63: 45563 | L63: 2024-09 | M63: Ativo | O63: =IF(M63="Cancelado",N63-K63,TODAY()-K63) -> 606 | P63: =IF(O63<=30,"Até 30 dias",IF(O63<=90,"31 a 90 dias",IF(O63<=180,"91 a 180 dias",IF(O63<=365,"181 a 365 dias","Mais de 1 ano")))) -> Mais de 1 ano | Q63: =IF(M63="Cancelado",1,0) -> 0 | R63: 8 | S63: =IF(Q63=1,J63,0) -> 0 | T63: =IF(R63<=6,"Detrator",IF(R63<=8,"Neutro","Promotor")) -> Neutro | U63: =IF(Q63=1,"Alto risco",IF(R63<=6,"Alto risco",IF(R63<=8,"Médio risco","Baixo risco"))) -> Médio risco | V63: 0 | W63: 59 | X63: 130.82 | Y63: 20 | Z63: Baixo
A64: C0063 | B64: Diego Pereira | C64: Fortaleza | D64: CE | E64: 63 | F64: Pessoa Física | G64: Orgânico | H64: P003 | I64: =_xludf.XLOOKUP(H64,Base_Planos!$A:$A,Base_Planos!$B:$B,"Não encontrado") -> #NAME? | J64: =VLOOKUP(H64,Base_Planos!$A:$G,4,FALSE) -> 79.9 | K64: 45915 | L64: 2025-09 | M64: Ativo | O64: =IF(M64="Cancelado",N64-K64,TODAY()-K64) -> 254 | P64: =IF(O64<=30,"Até 30 dias",IF(O64<=90,"31 a 90 dias",IF(O64<=180,"91 a 180 dias",IF(O64<=365,"181 a 365 dias","Mais de 1 ano")))) -> 181 a 365 dias | Q64: =IF(M64="Cancelado",1,0) -> 0 | R64: 7 | S64: =IF(Q64=1,J64,0) -> 0 | T64: =IF(R64<=6,"Detrator",IF(R64<=8,"Neutro","Promotor")) -> Neutro | U64: =IF(Q64=1,"Alto risco",IF(R64<=6,"Alto risco",IF(R64<=8,"Médio risco","Baixo risco"))) -> Médio risco | V64: 0 | W64: 92 | X64: 76.04 | Y64: 8 | Z64: Baixo
A65: C0064 | B65: Fernanda Pereira | C65: Guarulhos | D65: SP | E65: 22 | F65: Pessoa Física | G65: Parceiro | H65: P002 | I65: =_xludf.XLOOKUP(H65,Base_Planos!$A:$A,Base_Planos!$B:$B,"Não encontrado") -> #NAME? | J65: =VLOOKUP(H65,Base_Planos!$A:$G,4,FALSE) -> 29.9 | K65: 45966 | L65: 2025-11 | M65: Ativo | O65: =IF(M65="Cancelado",N65-K65,TODAY()-K65) -> 203 | P65: =IF(O65<=30,"Até 30 dias",IF(O65<=90,"31 a 90 dias",IF(O65<=180,"91 a 180 dias",IF(O65<=365,"181 a 365 dias","Mais de 1 ano")))) -> 181 a 365 dias | Q65: =IF(M65="Cancelado",1,0) -> 0 | R65: 4 | S65: =IF(Q65=1,J65,0) -> 0 | T65: =IF(R65<=6,"Detrator",IF(R65<=8,"Neutro","Promotor")) -> Detrator | U65: =IF(Q65=1,"Alto risco",IF(R65<=6,"Alto risco",IF(R65<=8,"Médio risco","Baixo risco"))) -> Alto risco | V65: 0 | W65: 36 | X65: 31.39 | Y65: 6 | Z65: Alto
A66: C0065 | B66: Pedro Pereira | C66: Fortaleza | D66: CE | E66: 52 | F66: MEI | G66: YouTube | H66: P004 | I66: =_xludf.XLOOKUP(H66,Base_Planos!$A:$A,Base_Planos!$B:$B,"Não encontrado") -> #NAME? | J66: =VLOOKUP(H66,Base_Planos!$A:$G,4,FALSE) -> 59.9 | K66: 46039 | L66: 2026-01 | M66: Ativo | O66: =IF(M66="Cancelado",N66-K66,TODAY()-K66) -> 130 | P66: =IF(O66<=30,"Até 30 dias",IF(O66<=90,"31 a 90 dias",IF(O66<=180,"91 a 180 dias",IF(O66<=365,"181 a 365 dias","Mais de 1 ano")))) -> 91 a 180 dias | Q66: =IF(M66="Cancelado",1,0) -> 0 | R66: 6 | S66: =IF(Q66=1,J66,0) -> 0 | T66: =IF(R66<=6,"Detrator",IF(R66<=8,"Neutro","Promotor")) -> Detrator | U66: =IF(Q66=1,"Alto risco",IF(R66<=6,"Alto risco",IF(R66<=8,"Médio risco","Baixo risco"))) -> Alto risco | V66: 0 | W66: 63 | X66: 57.77 | Y66: 4 | Z66: Baixo
A67: C0066 | B67: Henrique Araújo | C67: São Paulo | D67: SP | E67: 38 | F67: Pequena Empresa | G67: Parceiro | H67: P003 | I67: =_xludf.XLOOKUP(H67,Base_Planos!$A:$A,Base_Planos!$B:$B,"Não encontrado") -> #NAME? | J67: =VLOOKUP(H67,Base_Planos!$A:$G,4,FALSE) -> 79.9 | K67: 45238 | L67: 2023-11 | M67: Ativo | O67: =IF(M67="Cancelado",N67-K67,TODAY()-K67) -> 931 | P67: =IF(O67<=30,"Até 30 dias",IF(O67<=90,"31 a 90 dias",IF(O67<=180,"91 a 180 dias",IF(O67<=365,"181 a 365 dias","Mais de 1 ano")))) -> Mais de 1 ano | Q67: =IF(M67="Cancelado",1,0) -> 0 | R67: 7 | S67: =IF(Q67=1,J67,0) -> 0 | T67: =IF(R67<=6,"Detrator",IF(R67<=8,"Neutro","Promotor")) -> Neutro | U67: =IF(Q67=1,"Alto risco",IF(R67<=6,"Alto risco",IF(R67<=8,"Médio risco","Baixo risco"))) -> Médio risco | V67: 3 | W67: 53 | X67: 69.52 | Y67: 31 | Z67: Baixo
... A69: C0068 | B69: Marina Oliveira | C69: Guarulhos | D69: SP | E69: 39 | F69: Média Empresa | G69: Parceiro | H69: P007 | I69: =_xludf.XLOOKUP(H69,Base_Planos!$A:$A,Base_Planos!$B:$B,"Não encontrado") -> #NAME? | J69: =VLOOKUP(H69,Base_Planos!$A:$G,4,FALSE) -> 399.9 | K69: 45926 | L69: 2025-09 | M69: Ativo | O69: =IF(M69="Cancelado",N69-K69,TODAY()-K69) -> 243 | P69: =IF(O69<=30,"Até 30 dias",IF(O69<=90,"31 a 90 dias",IF(O69<=180,"91 a 180 dias",IF(O69<=365,"181 a 365 dias","Mais de 1 ano")))) -> 181 a 365 dias | Q69: =IF(M69="Cancelado",1,0) -> 0 | R69: 8 | S69: =IF(Q69=1,J69,0) -> 0 | T69: =IF(R69<=6,"Detrator",IF(R69<=8,"Neutro","Promotor")) -> Neutro | U69: =IF(Q69=1,"Alto risco",IF(R69<=6,"Alto risco",IF(R69<=8,"Médio risco","Baixo risco"))) -> Médio risco | V69: 1 | W69: 59 | X69: 419.69 | Y69: 8 | Z69: Baixo
A70: C0069 | B70: Zeca Oliveira | C70: Salvador | D70: BA | E70: 24 | F70: Pequena Empresa | G70: Instagram | H70: P003 | I70: =_xludf.XLOOKUP(H70,Base_Planos!$A:$A,Base_Planos!$B:$B,"Não encontrado") -> #NAME? | J70: =VLOOKUP(H70,Base_Planos!$A:$G,4,FALSE) -> 79.9 | K70: 45540 | L70: 2024-09 | M70: Cancelado | N70: 45719 | O70: =IF(M70="Cancelado",N70-K70,TODAY()-K70) -> 179 | P70: =IF(O70<=30,"Até 30 dias",IF(O70<=90,"31 a 90 dias",IF(O70<=180,"91 a 180 dias",IF(O70<=365,"181 a 365 dias","Mais de 1 ano")))) -> 91 a 180 dias | Q70: =IF(M70="Cancelado",1,0) -> 1 | R70: 0 | S70: =IF(Q70=1,J70,0) -> 79.9 | T70: =IF(R70<=6,"Detrator",IF(R70<=8,"Neutro","Promotor")) -> Detrator | U70: =IF(Q70=1,"Alto risco",IF(R70<=6,"Alto risco",IF(R70<=8,"Médio risco","Baixo risco"))) -> Alto risco | V70: 0 | W70: 71 | X70: 74.5 | Y70: 5 | Z70: Alto
A71: C0070 | B71: Wesley Lima | C71: Belo Horizonte | D71: MG | E71: 29 | F71: Pessoa Física | G71: Parceiro | H71: P004 | I71: =_xludf.XLOOKUP(H71,Base_Planos!$A:$A,Base_Planos!$B:$B,"Não encontrado") -> #NAME? | J71: =VLOOKUP(H71,Base_Planos!$A:$G,4,FALSE) -> 59.9 | K71: 45420 | L71: 2024-05 | M71: Ativo | O71: =IF(M71="Cancelado",N71-K71,TODAY()-K71) -> 749 | P71: =IF(O71<=30,"Até 30 dias",IF(O71<=90,"31 a 90 dias",IF(O71<=180,"91 a 180 dias",IF(O71<=365,"181 a 365 dias","Mais de 1 ano")))) -> Mais de 1 ano | Q71: =IF(M71="Cancelado",1,0) -> 0 | R71: 7 | S71: =IF(Q71=1,J71,0) -> 0 | T71: =IF(R71<=6,"Detrator",IF(R71<=8,"Neutro","Promotor")) -> Neutro | U71: =IF(Q71=1,"Alto risco",IF(R71<=6,"Alto risco",IF(R71<=8,"Médio risco","Baixo risco"))) -> Médio risco | V71: 0 | W71: 48 | X71: 53.97 | Y71: 24 | Z71: Baixo
A72: C0071 | B72: Ana Melo | C72: Porto Alegre | D72: RS | E72: 61 | F72: MEI | G72: Instagram | H72: P003 | I72: =_xludf.XLOOKUP(H72,Base_Planos!$A:$A,Base_Planos!$B:$B,"Não encontrado") -> #NAME? | J72: =VLOOKUP(H72,Base_Planos!$A:$G,4,FALSE) -> 79.9 | K72: 45634 | L72: 2024-12 | M72: Ativo | O72: =IF(M72="Cancelado",N72-K72,TODAY()-K72) -> 535 | P72: =IF(O72<=30,"Até 30 dias",IF(O72<=90,"31 a 90 dias",IF(O72<=180,"91 a 180 dias",IF(O72<=365,"181 a 365 dias","Mais de 1 ano")))) -> Mais de 1 ano | Q72: =IF(M72="Cancelado",1,0) -> 0 | R72: 9 | S72: =IF(Q72=1,J72,0) -> 0 | T72: =IF(R72<=6,"Detrator",IF(R72<=8,"Neutro","Promotor")) -> Promotor | U72: =IF(Q72=1,"Alto risco",IF(R72<=6,"Alto risco",IF(R72<=8,"Médio risco","Baixo risco"))) -> Baixo risco | V72: 1 | W72: 100 | X72: 72.74 | Y72: 17 | Z72: Baixo
A73: C0072 | B73: Marina Barbosa | C73: Rio de Janeiro | D73: RJ | E73: 33 | F73: MEI | G73: YouTube | H73: P004 | I73: =_xludf.XLOOKUP(H73,Base_Planos!$A:$A,Base_Planos!$B:$B,"Não encontrado") -> #NAME? | J73: =VLOOKUP(H73,Base_Planos!$A:$G,4,FALSE) -> 59.9 | K73: 45531 | L73: 2024-08 | M73: Ativo | O73: =IF(M73="Cancelado",N73-K73,TODAY()-K73) -> 638 | P73: =IF(O73<=30,"Até 30 dias",IF(O73<=90,"31 a 90 dias",IF(O73<=180,"91 a 180 dias",IF(O73<=365,"181 a 365 dias","Mais de 1 ano")))) -> Mais de 1 ano | Q73: =IF(M73="Cancelado",1,0) -> 0 | R73: 0 | S73: =IF(Q73=1,J73,0) -> 0 | T73: =IF(R73<=6,"Detrator",IF(R73<=8,"Neutro","Promotor")) -> Detrator | U73: =IF(Q73=1,"Alto risco",IF(R73<=6,"Alto risco",IF(R73<=8,"Médio risco","Baixo risco"))) -> Alto risco | V73: 0 | W73: 51 | X73: 59.13 | Y73: 21 | Z73: Alto
A74: C0073 | B74: Zeca Santos | C74: Campinas | D74: SP | E74: 65 | F74: MEI | G74: Orgânico | H74: P005 | I74: =_xludf.XLOOKUP(H74,Base_Planos!$A:$A,Base_Planos!$B:$B,"Não encontrado") -> #NAME? | J74: =VLOOKUP(H74,Base_Planos!$A:$G,4,FALSE) -> 149.9 | K74: 45398 | L74: 2024-04 | M74: Ativo | O74: =IF(M74="Cancelado",N74-K74,TODAY()-K74) -> 771 | P74: =IF(O74<=30,"Até 30 dias",IF(O74<=90,"31 a 90 dias",IF(O74<=180,"91 a 180 dias",IF(O74<=365,"181 a 365 dias","Mais de 1 ano")))) -> Mais de 1 ano | Q74: =IF(M74="Cancelado",1,0) -> 0 | R74: 9 | S74: =IF(Q74=1,J74,0) -> 0 | T74: =IF(R74<=6,"Detrator",IF(R74<=8,"Neutro","Promotor")) -> Promotor | U74: =IF(Q74=1,"Alto risco",IF(R74<=6,"Alto risco",IF(R74<=8,"Médio risco","Baixo risco"))) -> Baixo risco | V74: 0 | W74: 38 | X74: 150.07 | Y74: 25 | Z74: Baixo
A75: C0074 | B75: Bianca Pereira | C75: Osasco | D75: SP | E75: 24 | F75: Média Empresa | G75: Google Ads | H75: P002 | I75: =_xludf.XLOOKUP(H75,Base_Planos!$A:$A,Base_Planos!$B:$B,"Não encontrado") -> #NAME? | J75: =VLOOKUP(H75,Base_Planos!$A:$G,4,FALSE) -> 29.9 | K75: 45829 | L75: 2025-06 | M75: Cancelado | N75: 46071 | O75: =IF(M75="Cancelado",N75-K75,TODAY()-K75) -> 242 | P75: =IF(O75<=30,"Até 30 dias",IF(O75<=90,"31 a 90 dias",IF(O75<=180,"91 a 180 dias",IF(O75<=365,"181 a 365 dias","Mais de 1 ano")))) -> 181 a 365 dias | Q75: =IF(M75="Cancelado",1,0) -> 1 | R75: 0 | S75: =IF(Q75=1,J75,0) -> 29.9 | T75: =IF(R75<=6,"Detrator",IF(R75<=8,"Neutro","Promotor")) -> Detrator | U75: =IF(Q75=1,"Alto risco",IF(R75<=6,"Alto risco",IF(R75<=8,"Médio risco","Baixo risco"))) -> Alto risco | V75: 0 | W75: 35 | X75: 26.21 | Y75: 8 | Z75: Médio
A76: C0075 | B76: Rafael Martins | C76: Goiânia | D76: GO | E76: 50 | F76: Média Empresa | G76: Indicação | H76: P002 | I76: =_xludf.XLOOKUP(H76,Base_Planos!$A:$A,Base_Planos!$B:$B,"Não encontrado") -> #NAME? | J76: =VLOOKUP(H76,Base_Planos!$A:$G,4,FALSE) -> 29.9 | K76: 45913 | L76: 2025-09 | M76: Ativo | O76: =IF(M76="Cancelado",N76-K76,TODAY()-K76) -> 256 | P76: =IF(O76<=30,"Até 30 dias",IF(O76<=90,"31 a 90 dias",IF(O76<=180,"91 a 180 dias",IF(O76<=365,"181 a 365 dias","Mais de 1 ano")))) -> 181 a 365 dias | Q76: =IF(M76="Cancelado",1,0) -> 0 | R76: 4 | S76: =IF(Q76=1,J76,0) -> 0 | T76: =IF(R76<=6,"Detrator",IF(R76<=8,"Neutro","Promotor")) -> Detrator | U76: =IF(Q76=1,"Alto risco",IF(R76<=6,"Alto risco",IF(R76<=8,"Médio risco","Baixo risco"))) -> Alto risco | V76: 0 | W76: 31 | X76: 26.26 | Y76: 8 | Z76: Alto
A77: C0076 | B77: Henrique Carvalho | C77: Guarulhos | D77: SP | E77: 53 | F77: MEI | G77: Parceiro | H77: P001 | I77: =_xludf.XLOOKUP(H77,Base_Planos!$A:$A,Base_Planos!$B:$B,"Não encontrado") -> #NAME? | J77: =VLOOKUP(H77,Base_Planos!$A:$G,4,FALSE) -> 39.9 | K77: 46025 | L77: 2026-01 | M77: Ativo | O77: =IF(M77="Cancelado",N77-K77,TODAY()-K77) -> 144 | P77: =IF(O77<=30,"Até 30 dias",IF(O77<=90,"31 a 90 dias",IF(O77<=180,"91 a 180 dias",IF(O77<=365,"181 a 365 dias","Mais de 1 ano")))) -> 91 a 180 dias | Q77: =IF(M77="Cancelado",1,0) -> 0 | R77: 1 | S77: =IF(Q77=1,J77,0) -> 0 | T77: =IF(R77<=6,"Detrator",IF(R77<=8,"Neutro","Promotor")) -> Detrator | U77: =IF(Q77=1,"Alto risco",IF(R77<=6,"Alto risco",IF(R77<=8,"Médio risco","Baixo risco"))) -> Alto risco | V77: 1 | W77: 68 | X77: 40.48 | Y77: 4 | Z77: Médio
A78: C0077 | B78: Lucas Souza | C78: Osasco | D78: SP | E78: 32 | F78: MEI | G78: YouTube | H78: P006 | I78: =_xludf.XLOOKUP(H78,Base_Planos!$A:$A,Base_Planos!$B:$B,"Não encontrado") -> #NAME? | J78: =VLOOKUP(H78,Base_Planos!$A:$G,4,FALSE) -> 119.9 | K78: 45380 | L78: 2024-03 | M78: Cancelado | N78: 45828 | O78: =IF(M78="Cancelado",N78-K78,TODAY()-K78) -> 448 | P78: =IF(O78<=30,"Até 30 dias",IF(O78<=90,"31 a 90 dias",IF(O78<=180,"91 a 180 dias",IF(O78<=365,"181 a 365 dias","Mais de 1 ano")))) -> Mais de 1 ano | Q78: =IF(M78="Cancelado",1,0) -> 1 | R78: 10 | S78: =IF(Q78=1,J78,0) -> 119.9 | T78: =IF(R78<=6,"Detrator",IF(R78<=8,"Neutro","Promotor")) -> Promotor | U78: =IF(Q78=1,"Alto risco",IF(R78<=6,"Alto risco",IF(R78<=8,"Médio risco","Baixo risco"))) -> Alto risco | V78: 3 | W78: 77 | X78: 105.27 | Y78: 14 | Z78: Médio
A79: C0078 | B79: Bruno Gomes | C79: Fortaleza | D79: CE | E79: 25 | F79: Pessoa Física | G79: Indicação | H79: P003 | I79: =_xludf.XLOOKUP(H79,Base_Planos!$A:$A,Base_Planos!$B:$B,"Não encontrado") -> #NAME? | J79: =VLOOKUP(H79,Base_Planos!$A:$G,4,FALSE) -> 79.9 | K79: 45686 | L79: 2025-01 | M79: Ativo | O79: =IF(M79="Cancelado",N79-K79,TODAY()-K79) -> 483 | P79: =IF(O79<=30,"Até 30 dias",IF(O79<=90,"31 a 90 dias",IF(O79<=180,"91 a 180 dias",IF(O79<=365,"181 a 365 dias","Mais de 1 ano")))) -> Mais de 1 ano | Q79: =IF(M79="Cancelado",1,0) -> 0 | R79: 10 | S79: =IF(Q79=1,J79,0) -> 0 | T79: =IF(R79<=6,"Detrator",IF(R79<=8,"Neutro","Promotor")) -> Promotor | U79: =IF(Q79=1,"Alto risco",IF(R79<=6,"Alto risco",IF(R79<=8,"Médio risco","Baixo risco"))) -> Baixo risco | V79: 0 | W79: 43 | X79: 79.53 | Y79: 16 | Z79: Médio
A80: C0079 | B80: Fernanda Araújo | C80: Osasco | D80: SP | E80: 24 | F80: Média Empresa | G80: Parceiro | H80: P006 | I80: =_xludf.XLOOKUP(H80,Base_Planos!$A:$A,Base_Planos!$B:$B,"Não encontrado") -> #NAME? | J80: =VLOOKUP(H80,Base_Planos!$A:$G,4,FALSE) -> 119.9 | K80: 45499 | L80: 2024-07 | M80: Cancelado | N80: 45900 | O80: =IF(M80="Cancelado",N80-K80,TODAY()-K80) -> 401 | P80: =IF(O80<=30,"Até 30 dias",IF(O80<=90,"31 a 90 dias",IF(O80<=180,"91 a 180 dias",IF(O80<=365,"181 a 365 dias","Mais de 1 ano")))) -> Mais de 1 ano | Q80: =IF(M80="Cancelado",1,0) -> 1 | R80: 0 | S80: =IF(Q80=1,J80,0) -> 119.9 | T80: =IF(R80<=6,"Detrator",IF(R80<=8,"Neutro","Promotor")) -> Detrator | U80: =IF(Q80=1,"Alto risco",IF(R80<=6,"Alto risco",IF(R80<=8,"Médio risco","Baixo risco"))) -> Alto risco | V80: 0 | W80: 38 | X80: 118.36 | Y80: 13 | Z80: Médio
A81: C0080 | B81: Rafael Martins | C81: São Paulo | D81: SP | E81: 43 | F81: Pessoa Física | G81: Instagram | H81: P007 | I81: =_xludf.XLOOKUP(H81,Base_Planos!$A:$A,Base_Planos!$B:$B,"Não encontrado") -> #NAME? | J81: =VLOOKUP(H81,Base_Planos!$A:$G,4,FALSE) -> 399.9 | K81: 45858 | L81: 2025-07 | M81: Cancelado | N81: 46058 | O81: =IF(M81="Cancelado",N81-K81,TODAY()-K81) -> 200 | P81: =IF(O81<=30,"Até 30 dias",IF(O81<=90,"31 a 90 dias",IF(O81<=180,"91 a 180 dias",IF(O81<=365,"181 a 365 dias","Mais de 1 ano")))) -> 181 a 365 dias | Q81: =IF(M81="Cancelado",1,0) -> 1 | R81: 1 | S81: =IF(Q81=1,J81,0) -> 399.9 | T81: =IF(R81<=6,"Detrator",IF(R81<=8,"Neutro","Promotor")) -> Detrator | U81: =IF(Q81=1,"Alto risco",IF(R81<=6,"Alto risco",IF(R81<=8,"Médio risco","Baixo risco"))) -> Alto risco | V81: 1 | W81: 22 | X81: 349.99 | Y81: 6 | Z81: Médio
A82: C0081 | B82: Sofia Costa | C82: Rio de Janeiro | D82: RJ | E82: 53 | F82: Pessoa Física | G82: LinkedIn | H82: P005 | I82: =_xludf.XLOOKUP(H82,Base_Planos!$A:$A,Base_Planos!$B:$B,"Não encontrado") -> #NAME? | J82: =VLOOKUP(H82,Base_Planos!$A:$G,4,FALSE) -> 149.9 | K82: 45404 | L82: 2024-04 | M82: Cancelado | N82: 45582 | O82: =IF(M82="Cancelado",N82-K82,TODAY()-K82) -> 178 | P82: =IF(O82<=30,"Até 30 dias",IF(O82<=90,"31 a 90 dias",IF(O82<=180,"91 a 180 dias",IF(O82<=365,"181 a 365 dias","Mais de 1 ano")))) -> 91 a 180 dias | Q82: =IF(M82="Cancelado",1,0) -> 1 | R82: 5 | S82: =IF(Q82=1,J82,0) -> 149.9 | T82: =IF(R82<=6,"Detrator",IF(R82<=8,"Neutro","Promotor")) -> Detrator | U82: =IF(Q82=1,"Alto risco",IF(R82<=6,"Alto risco",IF(R82<=8,"Médio risco","Baixo risco"))) -> Alto risco | V82: 1 | W82: 8 | X82: 143.61 | Y82: 5 | Z82: Alto
A83: C0082 | B83: Caio Lima | C83: Rio de Janeiro | D83: RJ | E83: 60 | F83: Média Empresa | G83: Indicação | H83: P001 | I83: =_xludf.XLOOKUP(H83,Base_Planos!$A:$A,Base_Planos!$B:$B,"Não encontrado") -> #NAME? | J83: =VLOOKUP(H83,Base_Planos!$A:$G,4,FALSE) -> 39.9 | K83: 45414 | L83: 2024-05 | M83: Ativo | O83: =IF(M83="Cancelado",N83-K83,TODAY()-K83) -> 755 | P83: =IF(O83<=30,"Até 30 dias",IF(O83<=90,"31 a 90 dias",IF(O83<=180,"91 a 180 dias",IF(O83<=365,"181 a 365 dias","Mais de 1 ano")))) -> Mais de 1 ano | Q83: =IF(M83="Cancelado",1,0) -> 0 | R83: 9 | S83: =IF(Q83=1,J83,0) -> 0 | T83: =IF(R83<=6,"Detrator",IF(R83<=8,"Neutro","Promotor")) -> Promotor | U83: =IF(Q83=1,"Alto risco",IF(R83<=6,"Alto risco",IF(R83<=8,"Médio risco","Baixo risco"))) -> Baixo risco | V83: 0 | W83: 72 | X83: 38.11 | Y83: 25 | Z83: Baixo
A84: C0083 | B84: Zeca Oliveira | C84: Fortaleza | D84: CE | E84: 46 | F84: Pequena Empresa | G84: Instagram | H84: P003 | I84: =_xludf.XLOOKUP(H84,Base_Planos!$A:$A,Base_Planos!$B:$B,"Não encontrado") -> #NAME? | J84: =VLOOKUP(H84,Base_Planos!$A:$G,4,FALSE) -> 79.9 | K84: 45380 | L84: 2024-03 | M84: Ativo | O84: =IF(M84="Cancelado",N84-K84,TODAY()-K84) -> 789 | P84: =IF(O84<=30,"Até 30 dias",IF(O84<=90,"31 a 90 dias",IF(O84<=180,"91 a 180 dias",IF(O84<=365,"181 a 365 dias","Mais de 1 ano")))) -> Mais de 1 ano | Q84: =IF(M84="Cancelado",1,0) -> 0 | R84: 9 | S84: =IF(Q84=1,J84,0) -> 0 | T84: =IF(R84<=6,"Detrator",IF(R84<=8,"Neutro","Promotor")) -> Promotor | U84: =IF(Q84=1,"Alto risco",IF(R84<=6,"Alto risco",IF(R84<=8,"Médio risco","Baixo risco"))) -> Baixo risco | V84: 2 | W84: 70 | X84: 75.23 | Y84: 26 | Z84: Médio
A85: C0084 | B85: Ana Santos | C85: Fortaleza | D85: CE | E85: 43 | F85: MEI | G85: Instagram | H85: P003 | I85: =_xludf.XLOOKUP(H85,Base_Planos!$A:$A,Base_Planos!$B:$B,"Não encontrado") -> #NAME? | J85: =VLOOKUP(H85,Base_Planos!$A:$G,4,FALSE) -> 79.9 | K85: 45835 | L85: 2025-06 | M85: Cancelado | N85: 46164 | O85: =IF(M85="Cancelado",N85-K85,TODAY()-K85) -> 329 | P85: =IF(O85<=30,"Até 30 dias",IF(O85<=90,"31 a 90 dias",IF(O85<=180,"91 a 180 dias",IF(O85<=365,"181 a 365 dias","Mais de 1 ano")))) -> 181 a 365 dias | Q85: =IF(M85="Cancelado",1,0) -> 1 | R85: 1 | S85: =IF(Q85=1,J85,0) -> 79.9 | T85: =IF(R85<=6,"Detrator",IF(R85<=8,"Neutro","Promotor")) -> Detrator | U85: =IF(Q85=1,"Alto risco",IF(R85<=6,"Alto risco",IF(R85<=8,"Médio risco","Baixo risco"))) -> Alto risco | V85: 0 | W85: 42 | X85: 73.11 | Y85: 10 | Z85: Alto
A86: C0085 | B86: Thiago Rocha | C86: Porto Alegre | D86: RS | E86: 47 | F86: MEI | G86: Parceiro | H86: P001 | I86: =_xludf.XLOOKUP(H86,Base_Planos!$A:$A,Base_Planos!$B:$B,"Não encontrado") -> #NAME? | J86: =VLOOKUP(H86,Base_Planos!$A:$G,4,FALSE) -> 39.9 | K86: 45161 | L86: 2023-08 | M86: Cancelado | N86: 45653 | O86: =IF(M86="Cancelado",N86-K86,TODAY()-K86) -> 492 | P86: =IF(O86<=30,"Até 30 dias",IF(O86<=90,"31 a 90 dias",IF(O86<=180,"91 a 180 dias",IF(O86<=365,"181 a 365 dias","Mais de 1 ano")))) -> Mais de 1 ano | Q86: =IF(M86="Cancelado",1,0) -> 1 | R86: 10 | S86: =IF(Q86=1,J86,0) -> 39.9 | T86: =IF(R86<=6,"Detrator",IF(R86<=8,"Neutro","Promotor")) -> Promotor | U86: =IF(Q86=1,"Alto risco",IF(R86<=6,"Alto risco",IF(R86<=8,"Médio risco","Baixo risco"))) -> Alto risco | V86: 1 | W86: 18 | X86: 37.22 | Y86: 16 | Z86: Médio
A87: C0086 | B87: Daniela Melo | C87: Salvador | D87: BA | E87: 44 | F87: Pequena Empresa | G87: YouTube | H87: P003 | I87: =_xludf.XLOOKUP(H87,Base_Planos!$A:$A,Base_Planos!$B:$B,"Não encontrado") -> #NAME? | J87: =VLOOKUP(H87,Base_Planos!$A:$G,4,FALSE) -> 79.9 | K87: 45449 | L87: 2024-06 | M87: Cancelado | N87: 45566 | O87: =IF(M87="Cancelado",N87-K87,TODAY()-K87) -> 117 | P87: =IF(O87<=30,"Até 30 dias",IF(O87<=90,"31 a 90 dias",IF(O87<=180,"91 a 180 dias",IF(O87<=365,"181 a 365 dias","Mais de 1 ano")))) -> 91 a 180 dias | Q87: =IF(M87="Cancelado",1,0) -> 1 | R87: 5 | S87: =IF(Q87=1,J87,0) -> 79.9 | T87: =IF(R87<=6,"Detrator",IF(R87<=8,"Neutro","Promotor")) -> Detrator | U87: =IF(Q87=1,"Alto risco",IF(R87<=6,"Alto risco",IF(R87<=8,"Médio risco","Baixo risco"))) -> Alto risco | V87: 0 | W87: 44 | X87: 74.82 | Y87: 3 | Z87: Médio
A88: C0087 | B88: Zeca Martins | C88: Santo André | D88: SP | E88: 26 | F88: MEI | G88: YouTube | H88: P004 | I88: =_xludf.XLOOKUP(H88,Base_Planos!$A:$A,Base_Planos!$B:$B,"Não encontrado") -> #NAME? | J88: =VLOOKUP(H88,Base_Planos!$A:$G,4,FALSE) -> 59.9 | K88: 45768 | L88: 2025-04 | M88: Ativo | O88: =IF(M88="Cancelado",N88-K88,TODAY()-K88) -> 401 | P88: =IF(O88<=30,"Até 30 dias",IF(O88<=90,"31 a 90 dias",IF(O88<=180,"91 a 180 dias",IF(O88<=365,"181 a 365 dias","Mais de 1 ano")))) -> Mais de 1 ano | Q88: =IF(M88="Cancelado",1,0) -> 0 | R88: 5 | S88: =IF(Q88=1,J88,0) -> 0 | T88: =IF(R88<=6,"Detrator",IF(R88<=8,"Neutro","Promotor")) -> Detrator | U88: =IF(Q88=1,"Alto risco",IF(R88<=6,"Alto risco",IF(R88<=8,"Médio risco","Baixo risco"))) -> Alto risco | V88: 0 | W88: 9 | X88: 51.53 | Y88: 13 | Z88: Alto
A89: C0088 | B89: João Nascimento | C89: Porto Alegre | D89: RS | E89: 40 | F89: Pessoa Física | G89: LinkedIn | H89: P001 | I89: =_xludf.XLOOKUP(H89,Base_Planos!$A:$A,Base_Planos!$B:$B,"Não encontrado") -> #NAME? | J89: =VLOOKUP(H89,Base_Planos!$A:$G,4,FALSE) -> 39.9 | K89: 45914 | L89: 2025-09 | M89: Cancelado | N89: 46015 | O89: =IF(M89="Cancelado",N89-K89,TODAY()-K89) -> 101 | P89: =IF(O89<=30,"Até 30 dias",IF(O89<=90,"31 a 90 dias",IF(O89<=180,"91 a 180 dias",IF(O89<=365,"181 a 365 dias","Mais de 1 ano")))) -> 91 a 180 dias | Q89: =IF(M89="Cancelado",1,0) -> 1 | R89: 3 | S89: =IF(Q89=1,J89,0) -> 39.9 | T89: =IF(R89<=6,"Detrator",IF(R89<=8,"Neutro","Promotor")) -> Detrator | U89: =IF(Q89=1,"Alto risco",IF(R89<=6,"Alto risco",IF(R89<=8,"Médio risco","Baixo risco"))) -> Alto risco | V89: 0 | W89: 35 | X89: 40.36 | Y89: 3 | Z89: Alto
A90: C0089 | B90: Enzo Dias | C90: Santo André | D90: SP | E90: 57 | F90: Pequena Empresa | G90: Google Ads | H90: P004 | I90: =_xludf.XLOOKUP(H90,Base_Planos!$A:$A,Base_Planos!$B:$B,"Não encontrado") -> #NAME? | J90: =VLOOKUP(H90,Base_Planos!$A:$G,4,FALSE) -> 59.9 | K90: 45474 | L90: 2024-07 | M90: Ativo | O90: =IF(M90="Cancelado",N90-K90,TODAY()-K90) -> 695 | P90: =IF(O90<=30,"Até 30 dias",IF(O90<=90,"31 a 90 dias",IF(O90<=180,"91 a 180 dias",IF(O90<=365,"181 a 365 dias","Mais de 1 ano")))) -> Mais de 1 ano | Q90: =IF(M90="Cancelado",1,0) -> 0 | R90: 0 | S90: =IF(Q90=1,J90,0) -> 0 | T90: =IF(R90<=6,"Detrator",IF(R90<=8,"Neutro","Promotor")) -> Detrator | U90: =IF(Q90=1,"Alto risco",IF(R90<=6,"Alto risco",IF(R90<=8,"Médio risco","Baixo risco"))) -> Alto risco | V90: 0 | W90: 96 | X90: 50.99 | Y90: 23 | Z90: Médio
A91: C0090 | B91: Enzo Pereira | C91: Campinas | D91: SP | E91: 60 | F91: MEI | G91: Indicação | H91: P005 | I91: =_xludf.XLOOKUP(H91,Base_Planos!$A:$A,Base_Planos!$B:$B,"Não encontrado") -> #NAME? | J91: =VLOOKUP(H91,Base_Planos!$A:$G,4,FALSE) -> 149.9 | K91: 44989 | L91: 2023-03 | M91: Cancelado | N91: 45776 | O91: =IF(M91="Cancelado",N91-K91,TODAY()-K91) -> 787 | P91: =IF(O91<=30,"Até 30 dias",IF(O91<=90,"31 a 90 dias",IF(O91<=180,"91 a 180 dias",IF(O91<=365,"181 a 365 dias","Mais de 1 ano")))) -> Mais de 1 ano | Q91: =IF(M91="Cancelado",1,0) -> 1 | R91: 1 | S91: =IF(Q91=1,J91,0) -> 149.9 | T91: =IF(R91<=6,"Detrator",IF(R91<=8,"Neutro","Promotor")) -> Detrator | U91: =IF(Q91=1,"Alto risco",IF(R91<=6,"Alto risco",IF(R91<=8,"Médio risco","Baixo risco"))) -> Alto risco | V91: 0 | W91: 37 | X91: 137.14 | Y91: 26 | Z91: Alto
A92: C0091 | B92: Sofia Nascimento | C92: Rio de Janeiro | D92: RJ | E92: 21 | F92: Pessoa Física | G92: Google Ads | H92: P004 | I92: =_xludf.XLOOKUP(H92,Base_Planos!$A:$A,Base_Planos!$B:$B,"Não encontrado") -> #NAME? | J92: =VLOOKUP(H92,Base_Planos!$A:$G,4,FALSE) -> 59.9 | K92: 45484 | L92: 2024-07 | M92: Ativo | O92: =IF(M92="Cancelado",N92-K92,TODAY()-K92) -> 685 | P92: =IF(O92<=30,"Até 30 dias",IF(O92<=90,"31 a 90 dias",IF(O92<=180,"91 a 180 dias",IF(O92<=365,"181 a 365 dias","Mais de 1 ano")))) -> Mais de 1 ano | Q92: =IF(M92="Cancelado",1,0) -> 0 | R92: 7 | S92: =IF(Q92=1,J92,0) -> 0 | T92: =IF(R92<=6,"Detrator",IF(R92<=8,"Neutro","Promotor")) -> Neutro | U92: =IF(Q92=1,"Alto risco",IF(R92<=6,"Alto risco",IF(R92<=8,"Médio risco","Baixo risco"))) -> Médio risco | V92: 0 | W92: 29 | X92: 59.96 | Y92: 22 | Z92: Baixo
A93: C0092 | B93: Diego Martins | C93: Salvador | D93: BA | E93: 25 | F93: Pessoa Física | G93: E-mail marketing | H93: P003 | I93: =_xludf.XLOOKUP(H93,Base_Planos!$A:$A,Base_Planos!$B:$B,"Não encontrado") -> #NAME? | J93: =VLOOKUP(H93,Base_Planos!$A:$G,4,FALSE) -> 79.9 | K93: 45558 | L93: 2024-09 | M93: Cancelado | N93: 45804 | O93: =IF(M93="Cancelado",N93-K93,TODAY()-K93) -> 246 | P93: =IF(O93<=30,"Até 30 dias",IF(O93<=90,"31 a 90 dias",IF(O93<=180,"91 a 180 dias",IF(O93<=365,"181 a 365 dias","Mais de 1 ano")))) -> 181 a 365 dias | Q93: =IF(M93="Cancelado",1,0) -> 1 | R93: 0 | S93: =IF(Q93=1,J93,0) -> 79.9 | T93: =IF(R93<=6,"Detrator",IF(R93<=8,"Neutro","Promotor")) -> Detrator | U93: =IF(Q93=1,"Alto risco",IF(R93<=6,"Alto risco",IF(R93<=8,"Médio risco","Baixo risco"))) -> Alto risco | V93: 0 | W93: 100 | X93: 80.13 | Y93: 8 | Z93: Médio
A94: C0093 | B94: João Ribeiro | C94: Rio de Janeiro | D94: RJ | E94: 18 | F94: MEI | G94: Parceiro | H94: P001 | I94: =_xludf.XLOOKUP(H94,Base_Planos!$A:$A,Base_Planos!$B:$B,"Não encontrado") -> #NAME? | J94: =VLOOKUP(H94,Base_Planos!$A:$G,4,FALSE) -> 39.9 | K94: 45705 | L94: 2025-02 | M94: Ativo | O94: =IF(M94="Cancelado",N94-K94,TODAY()-K94) -> 464 | P94: =IF(O94<=30,"Até 30 dias",IF(O94<=90,"31 a 90 dias",IF(O94<=180,"91 a 180 dias",IF(O94<=365,"181 a 365 dias","Mais de 1 ano")))) -> Mais de 1 ano | Q94: =IF(M94="Cancelado",1,0) -> 0 | R94: 8 | S94: =IF(Q94=1,J94,0) -> 0 | T94: =IF(R94<=6,"Detrator",IF(R94<=8,"Neutro","Promotor")) -> Neutro | U94: =IF(Q94=1,"Alto risco",IF(R94<=6,"Alto risco",IF(R94<=8,"Médio risco","Baixo risco"))) -> Médio risco | V94: 2 | W94: 25 | X94: 34.49 | Y94: 15 | Z94: Médio
A95: C0094 | B95: Enzo Santos | C95: Salvador | D95: BA | E95: 19 | F95: MEI | G95: Instagram | H95: P006 | I95: =_xludf.XLOOKUP(H95,Base_Planos!$A:$A,Base_Planos!$B:$B,"Não encontrado") -> #NAME? | J95: =VLOOKUP(H95,Base_Planos!$A:$G,4,FALSE) -> 119.9 | K95: 46106 | L95: 2026-03 | M95: Cancelado | N95: 46137 | O95: =IF(M95="Cancelado",N95-K95,TODAY()-K95) -> 31 | P95: =IF(O95<=30,"Até 30 dias",IF(O95<=90,"31 a 90 dias",IF(O95<=180,"91 a 180 dias",IF(O95<=365,"181 a 365 dias","Mais de 1 ano")))) -> 31 a 90 dias | Q95: =IF(M95="Cancelado",1,0) -> 1 | R95: 6 | S95: =IF(Q95=1,J95,0) -> 119.9 | T95: =IF(R95<=6,"Detrator",IF(R95<=8,"Neutro","Promotor")) -> Detrator | U95: =IF(Q95=1,"Alto risco",IF(R95<=6,"Alto risco",IF(R95<=8,"Médio risco","Baixo risco"))) -> Alto risco | V95: 0 | W95: 37 | X95: 106.04 | Y95: 1 | Z95: Médio
A96: C0095 | B96: Thiago Melo | C96: Guarulhos | D96: SP | E96: 62 | F96: Média Empresa | G96: Instagram | H96: P003 | I96: =_xludf.XLOOKUP(H96,Base_Planos!$A:$A,Base_Planos!$B:$B,"Não encontrado") -> #NAME? | J96: =VLOOKUP(H96,Base_Planos!$A:$G,4,FALSE) -> 79.9 | K96: 45143 | L96: 2023-08 | M96: Ativo | O96: =IF(M96="Cancelado",N96-K96,TODAY()-K96) -> 1026 | P96: =IF(O96<=30,"Até 30 dias",IF(O96<=90,"31 a 90 dias",IF(O96<=180,"91 a 180 dias",IF(O96<=365,"181 a 365 dias","Mais de 1 ano")))) -> Mais de 1 ano | Q96: =IF(M96="Cancelado",1,0) -> 0 | R96: 3 | S96: =IF(Q96=1,J96,0) -> 0 | T96: =IF(R96<=6,"Detrator",IF(R96<=8,"Neutro","Promotor")) -> Detrator | U96: =IF(Q96=1,"Alto risco",IF(R96<=6,"Alto risco",IF(R96<=8,"Médio risco","Baixo risco"))) -> Alto risco | V96: 0 | W96: 68 | X96: 79.83 | Y96: 34 | Z96: Médio
A97: C0096 | B97: Henrique Ribeiro | C97: Santo André | D97: SP | E97: 28 | F97: Pessoa Física | G97: Instagram | H97: P003 | I97: =_xludf.XLOOKUP(H97,Base_Planos!$A:$A,Base_Planos!$B:$B,"Não encontrado") -> #NAME? | J97: =VLOOKUP(H97,Base_Planos!$A:$G,4,FALSE) -> 79.9 | K97: 45324 | L97: 2024-02 | M97: Cancelado | N97: 45459 | O97: =IF(M97="Cancelado",N97-K97,TODAY()-K97) -> 135 | P97: =IF(O97<=30,"Até 30 dias",IF(O97<=90,"31 a 90 dias",IF(O97<=180,"91 a 180 dias",IF(O97<=365,"181 a 365 dias","Mais de 1 ano")))) -> 91 a 180 dias | Q97: =IF(M97="Cancelado",1,0) -> 1 | R97: 5 | S97: =IF(Q97=1,J97,0) -> 79.9 | T97: =IF(R97<=6,"Detrator",IF(R97<=8,"Neutro","Promotor")) -> Detrator | U97: =IF(Q97=1,"Alto risco",IF(R97<=6,"Alto risco",IF(R97<=8,"Médio risco","Baixo risco"))) -> Alto risco | V97: 1 | W97: 100 | X97: 72.01 | Y97: 4 | Z97: Baixo
A98: C0097 | B98: Felipe Nascimento | C98: Belo Horizonte | D98: MG | E98: 59 | F98: Pessoa Física | G98: E-mail marketing | H98: P003 | I98: =_xludf.XLOOKUP(H98,Base_Planos!$A:$A,Base_Planos!$B:$B,"Não encontrado") -> #NAME? | J98: =VLOOKUP(H98,Base_Planos!$A:$G,4,FALSE) -> 79.9 | K98: 46081 | L98: 2026-02 | M98: Ativo | O98: =IF(M98="Cancelado",N98-K98,TODAY()-K98) -> 88 | P98: =IF(O98<=30,"Até 30 dias",IF(O98<=90,"31 a 90 dias",IF(O98<=180,"91 a 180 dias",IF(O98<=365,"181 a 365 dias","Mais de 1 ano")))) -> 31 a 90 dias | Q98: =IF(M98="Cancelado",1,0) -> 0 | R98: 9 | S98: =IF(Q98=1,J98,0) -> 0 | T98: =IF(R98<=6,"Detrator",IF(R98<=8,"Neutro","Promotor")) -> Promotor | U98: =IF(Q98=1,"Alto risco",IF(R98<=6,"Alto risco",IF(R98<=8,"Médio risco","Baixo risco"))) -> Baixo risco | V98: 0 | W98: 77 | X98: 77.89 | Y98: 2 | Z98: Baixo
A99: C0098 | B99: Enzo Ribeiro | C99: Belo Horizonte | D99: MG | E99: 46 | F99: Pessoa Física | G99: E-mail marketing | H99: P004 | I99: =_xludf.XLOOKUP(H99,Base_Planos!$A:$A,Base_Planos!$B:$B,"Não encontrado") -> #NAME? | J99: =VLOOKUP(H99,Base_Planos!$A:$G,4,FALSE) -> 59.9 | K99: 45489 | L99: 2024-07 | M99: Ativo | O99: =IF(M99="Cancelado",N99-K99,TODAY()-K99) -> 680 | P99: =IF(O99<=30,"Até 30 dias",IF(O99<=90,"31 a 90 dias",IF(O99<=180,"91 a 180 dias",IF(O99<=365,"181 a 365 dias","Mais de 1 ano")))) -> Mais de 1 ano | Q99: =IF(M99="Cancelado",1,0) -> 0 | R99: 9 | S99: =IF(Q99=1,J99,0) -> 0 | T99: =IF(R99<=6,"Detrator",IF(R99<=8,"Neutro","Promotor")) -> Promotor | U99: =IF(Q99=1,"Alto risco",IF(R99<=6,"Alto risco",IF(R99<=8,"Médio risco","Baixo risco"))) -> Baixo risco | V99: 0 | W99: 68 | X99: 51.6 | Y99: 22 | Z99: Baixo
A100: C0099 | B100: Daniela Gomes | C100: Rio de Janeiro | D100: RJ | E100: 59 | F100: Média Empresa | G100: Instagram | H100: P004 | I100: =_xludf.XLOOKUP(H100,Base_Planos!$A:$A,Base_Planos!$B:$B,"Não encontrado") -> #NAME? | J100: =VLOOKUP(H100,Base_Planos!$A:$G,4,FALSE) -> 59.9 | K100: 45965 | L100: 2025-11 | M100: Ativo | O100: =IF(M100="Cancelado",N100-K100,TODAY()-K100) -> 204 | P100: =IF(O100<=30,"Até 30 dias",IF(O100<=90,"31 a 90 dias",IF(O100<=180,"91 a 180 dias",IF(O100<=365,"181 a 365 dias","Mais de 1 ano")))) -> 181 a 365 dias | Q100: =IF(M100="Cancelado",1,0) -> 0 | R100: 6 | S100: =IF(Q100=1,J100,0) -> 0 | T100: =IF(R100<=6,"Detrator",IF(R100<=8,"Neutro","Promotor")) -> Detrator | U100: =IF(Q100=1,"Alto risco",IF(R100<=6,"Alto risco",IF(R100<=8,"Médio risco","Baixo risco"))) -> Alto risco | V100: 1 | W100: 65 | X100: 56.3 | Y100: 6 | Z100: Baixo
A101: C0100 | B101: Caio Teixeira | C101: Osasco | D101: SP | E101: 30 | F101: Pessoa Física | G101: E-mail marketing | H101: P003 | I101: =_xludf.XLOOKUP(H101,Base_Planos!$A:$A,Base_Planos!$B:$B,"Não encontrado") -> #NAME? | J101: =VLOOKUP(H101,Base_Planos!$A:$G,4,FALSE) -> 79.9 | K101: 45053 | L101: 2023-05 | M101: Ativo | O101: =IF(M101="Cancelado",N101-K101,TODAY()-K101) -> 1116 | P101: =IF(O101<=30,"Até 30 dias",IF(O101<=90,"31 a 90 dias",IF(O101<=180,"91 a 180 dias",IF(O101<=365,"181 a 365 dias","Mais de 1 ano")))) -> Mais de 1 ano | Q101: =IF(M101="Cancelado",1,0) -> 0 | R101: 7 | S101: =IF(Q101=1,J101,0) -> 0 | T101: =IF(R101<=6,"Detrator",IF(R101<=8,"Neutro","Promotor")) -> Neutro | U101: =IF(Q101=1,"Alto risco",IF(R101<=6,"Alto risco",IF(R101<=8,"Médio risco","Baixo risco"))) -> Médio risco | V101: 0 | W101: 93 | X101: 75.98 | Y101: 37 | Z101: Baixo
...

Sheet Base_Planos
A1: Plano_ID | B1: Nome_Plano | C1: Categoria | D1: Valor_Plano | E1: Limite_Usuarios | F1: Suporte | G1: Contrato_Meses
A2: P001 | B2: Basic Mensal | C2: Entrada | D2: 39.9 | E2: 1 | F2: E-mail | G2: 1
A3: P002 | B3: Basic Anual | C3: Entrada | D3: 29.9 | E3: 1 | F3: E-mail | G3: 12
A4: P003 | B4: Plus Mensal | C4: Intermediário | D4: 79.9 | E4: 3 | F4: Chat | G4: 1
A5: P004 | B5: Plus Anual | C5: Intermediário | D5: 59.9 | E5: 3 | F5: Chat | G5: 12
A6: P005 | B6: Premium Mensal | C6: Avançado | D6: 149.9 | E6: 10 | F6: Prioritário | G6: 1
A7: P006 | B7: Premium Anual | C7: Avançado | D7: 119.9 | E7: 10 | F7: Prioritário | G7: 12
A8: P007 | B8: Enterprise | C8: Corporativo | D8: 399.9 | E8: 50 | F8: Gerente de conta | G8: 12

Sheet Base_Interacoes
A1: ID_Interacao | B1: ID_Cliente | C1: Data_Interacao | D1: Tipo_Contato | E1: Canal_Atendimento | F1: Tempo_Resposta_Horas | G1: Resolvido | H1: Satisfacao_Pos_Atendimento
A2: I00001 | B2: C0470 | C2: 45091 | D2: Reclamação | E2: Chat | F2: 1.1 | G2: Não | H2: 3
A3: I00002 | B3: C0011 | C3: 46101 | D3: Dúvida | E3: WhatsApp | F3: 1.8 | G3: Sim | H3: 4
A4: I00003 | B4: C0037 | C4: 45480 | D4: Financeiro | E4: Telefone | F4: 3.7 | G4: Sim | H4: 4
A5: I00004 | B5: C0417 | C5: 45627 | D5: Dúvida | E5: Telefone | F5: 10.2 | G5: Sim | H5: 4
A6: I00005 | B6: C0289 | C6: 45473 | D6: Dúvida | E6: WhatsApp | F6: 20.1 | G6: Sim | H6: 3
A7: I00006 | B7: C0883 | C7: 45969 | D7: Downgrade | E7: Chat | F7: 13.3 | G7: Sim | H7: 1
A8: I00007 | B8: C0249 | C8: 45079 | D8: Dúvida | E8: Chat | F8: 1.3 | G8: Sim | H8: 1
A9: I00008 | B9: C0885 | C9: 45081 | D9: Dúvida | E9: Chat | F9: 10.7 | G9: Sim | H9: 5
A10: I00009 | B10: C0073 | C10: 45246 | D10: Problema técnico | E10: WhatsApp | F10: 8 | G10: Sim | H10: 1
A11: I00010 | B11: C0628 | C11: 45176 | D11: Dúvida | E11: E-mail | F11: 1.8 | G11: Sim | H11: 1
A12: I00011 | B12: C0191 | C12: 45114 | D12: Financeiro | E12: Chat | F12: 0.2 | G12: Sim | H12: 2
A13: I00012 | B13: C0216 | C13: 45029 | D13: Financeiro | E13: WhatsApp | F13: 3.1 | G13: Sim | H13: 4
... A2001: I02000 | B2001: C0066 | C2001: 45016 | D2001: Downgrade | E2001: Chat | F2001: 3.8 | G2001: Não | H2001: 1

Sheet Base_Cancelamentos
A1: ID_Cancelamento | B1: ID_Cliente | C1: Data_Cancelamento | D1: Motivo_Cancelamento | E1: Mes_Cancelamento | F1: Canal_Aquisicao_PROCX | G1: Plano_PROCX | H1: Tempo_Cliente_Meses_PROCV
A2: CAN0001 | B2: C0001 | C2: 45261 | D2: Migrou para concorrente | E2: 2023-12 | F2: =_xludf.XLOOKUP(B2,Base_Clientes!$A:$A,Base_Clientes!$G:$G,"Não encontrado") -> #NAME? | G2: =_xludf.XLOOKUP(B2,Base_Clientes!$A:$A,Base_Clientes!$I:$I,"Não encontrado") -> #NAME? | H2: =VLOOKUP(B2,Base_Clientes!$A:$Z,21,FALSE) -> Alto risco
A3: CAN0002 | B3: C0003 | C3: 46133 | D3: Cancelamento financeiro | E3: 2026-04 | F3: =_xludf.XLOOKUP(B3,Base_Clientes!$A:$A,Base_Clientes!$G:$G,"Não encontrado") -> #NAME? | G3: =_xludf.XLOOKUP(B3,Base_Clientes!$A:$A,Base_Clientes!$I:$I,"Não encontrado") -> #NAME? | H3: =VLOOKUP(B3,Base_Clientes!$A:$Z,21,FALSE) -> Alto risco
A4: CAN0003 | B4: C0004 | C4: 45887 | D4: Produto não atende | E4: 2025-08 | F4: =_xludf.XLOOKUP(B4,Base_Clientes!$A:$A,Base_Clientes!$G:$G,"Não encontrado") -> #NAME? | G4: =_xludf.XLOOKUP(B4,Base_Clientes!$A:$A,Base_Clientes!$I:$I,"Não encontrado") -> #NAME? | H4: =VLOOKUP(B4,Base_Clientes!$A:$Z,21,FALSE) -> Alto risco
A5: CAN0004 | B5: C0011 | C5: 46083 | D5: Problemas técnicos | E5: 2026-03 | F5: =_xludf.XLOOKUP(B5,Base_Clientes!$A:$A,Base_Clientes!$G:$G,"Não encontrado") -> #NAME? | G5: =_xludf.XLOOKUP(B5,Base_Clientes!$A:$A,Base_Clientes!$I:$I,"Não encontrado") -> #NAME? | H5: =VLOOKUP(B5,Base_Clientes!$A:$Z,21,FALSE) -> Alto risco
A6: CAN0005 | B6: C0013 | C6: 45709 | D6: Suporte insatisfatório | E6: 2025-02 | F6: =_xludf.XLOOKUP(B6,Base_Clientes!$A:$A,Base_Clientes!$G:$G,"Não encontrado") -> #NAME? | G6: =_xludf.XLOOKUP(B6,Base_Clientes!$A:$A,Base_Clientes!$I:$I,"Não encontrado") -> #NAME? | H6: =VLOOKUP(B6,Base_Clientes!$A:$Z,21,FALSE) -> Alto risco
A7: CAN0006 | B7: C0015 | C7: 45352 | D7: Migrou para concorrente | E7: 2024-03 | F7: =_xludf.XLOOKUP(B7,Base_Clientes!$A:$A,Base_Clientes!$G:$G,"Não encontrado") -> #NAME? | G7: =_xludf.XLOOKUP(B7,Base_Clientes!$A:$A,Base_Clientes!$I:$I,"Não encontrado") -> #NAME? | H7: =VLOOKUP(B7,Base_Clientes!$A:$Z,21,FALSE) -> Alto risco
A8: CAN0007 | B8: C0018 | C8: 46052 | D8: Suporte insatisfatório | E8: 2026-01 | F8: =_xludf.XLOOKUP(B8,Base_Clientes!$A:$A,Base_Clientes!$G:$G,"Não encontrado") -> #NAME? | G8: =_xludf.XLOOKUP(B8,Base_Clientes!$A:$A,Base_Clientes!$I:$I,"Não encontrado") -> #NAME? | H8: =VLOOKUP(B8,Base_Clientes!$A:$Z,21,FALSE) -> Alto risco
A9: CAN0008 | B9: C0022 | C9: 46105 | D9: Produto não atende | E9: 2026-03 | F9: =_xludf.XLOOKUP(B9,Base_Clientes!$A:$A,Base_Clientes!$G:$G,"Não encontrado") -> #NAME? | G9: =_xludf.XLOOKUP(B9,Base_Clientes!$A:$A,Base_Clientes!$I:$I,"Não encontrado") -> #NAME? | H9: =VLOOKUP(B9,Base_Clientes!$A:$Z,21,FALSE) -> Alto risco
A10: CAN0009 | B10: C0023 | C10: 45604 | D10: Produto não atende | E10: 2024-11 | F10: =_xludf.XLOOKUP(B10,Base_Clientes!$A:$A,Base_Clientes!$G:$G,"Não encontrado") -> #NAME? | G10: =_xludf.XLOOKUP(B10,Base_Clientes!$A:$A,Base_Clientes!$I:$I,"Não encontrado") -> #NAME? | H10: =VLOOKUP(B10,Base_Clientes!$A:$Z,21,FALSE) -> Alto risco
A11: CAN0010 | B11: C0025 | C11: 46123 | D11: Suporte insatisfatório | E11: 2026-04 | F11: =_xludf.XLOOKUP(B11,Base_Clientes!$A:$A,Base_Clientes!$G:$G,"Não encontrado") -> #NAME? | G11: =_xludf.XLOOKUP(B11,Base_Clientes!$A:$A,Base_Clientes!$I:$I,"Não encontrado") -> #NAME? | H11: =VLOOKUP(B11,Base_Clientes!$A:$Z,21,FALSE) -> Alto risco
A12: CAN0011 | B12: C0026 | C12: 45946 | D12: Suporte insatisfatório | E12: 2025-10 | F12: =_xludf.XLOOKUP(B12,Base_Clientes!$A:$A,Base_Clientes!$G:$G,"Não encontrado") -> #NAME? | G12: =_xludf.XLOOKUP(B12,Base_Clientes!$A:$A,Base_Clientes!$I:$I,"Não encontrado") -> #NAME? | H12: =VLOOKUP(B12,Base_Clientes!$A:$Z,21,FALSE) -> Alto risco
A13: CAN0012 | B13: C0028 | C13: 46120 | D13: Contrato encerrado | E13: 2026-04 | F13: =_xludf.XLOOKUP(B13,Base_Clientes!$A:$A,Base_Clientes!$G:$G,"Não encontrado") -> #NAME? | G13: =_xludf.XLOOKUP(B13,Base_Clientes!$A:$A,Base_Clientes!$I:$I,"Não encontrado") -> #NAME? | H13: =VLOOKUP(B13,Base_Clientes!$A:$Z,21,FALSE) -> Alto risco
... A293: CAN0292 | B293: C0999 | C293: 46034 | D293: Pouco uso | E293: 2026-01 | F293: =_xludf.XLOOKUP(B293,Base_Clientes!$A:$A,Base_Clientes!$G:$G,"Não encontrado") -> #NAME? | G293: =_xludf.XLOOKUP(B293,Base_Clientes!$A:$A,Base_Clientes!$I:$I,"Não encontrado") -> #NAME? | H293: =VLOOKUP(B293,Base_Clientes!$A:$Z,21,FALSE) -> Alto risco

Sheet Consultas_PROCV_PROCX
A1: Exercícios de PROCX e PROCV para análise de cancelamento de clientes
A3: Digite um ID_Cliente aqui: | B3: C0001
A5: Campo buscado | B5: Resultado
A6: Nome do cliente | B6: =_xlfn.XLOOKUP($B$3,Base_Clientes!$A:$A,Base_Clientes!$B:$B,"Não encontrado") -> Valentina Souza
A7: Status | B7: =_xlfn.XLOOKUP($B$3,Base_Clientes!$A:$A,Base_Clientes!$H:$H,"Não encontrado") -> P001
A8: Plano | B8: =_xlfn.XLOOKUP(B7,Base_Planos!A:A,Base_Planos!B:B,"Não encontrado") -> Basic Mensal
A9: Valor do plano | B9: =VLOOKUP($B$3,Base_Clientes!$A:$Z,10,FALSE) -> 39.9
A10: Motivo de cancelamento | B10: =_xlfn.XLOOKUP($B$3,Base_Clientes!$A:$A,Base_Clientes!$W:$W,"Não encontrado") -> 21
A11: Risco de churn | B11: =_xlfn.XLOOKUP($B$3,Base_Clientes!$A:$A,Base_Clientes!$Z:$Z,"Não encontrado") -> Médio
A13: Fórmulas em português para você treinar no Excel BR
A14: Objetivo | B14: Fórmula em inglês no arquivo | C14: Como ficaria em PT-BR
A15: Buscar nome pelo ID | B15: =XLOOKUP($B$3,Base_Clientes!$A:$A,Base_Clientes!$B:$B,"Não encontrado") | C15: =PROCX($B$3;Base_Clientes!$A:$A;Base_Clientes!$B:$B;"Não encontrado")
A16: Buscar status pelo ID | B16: =XLOOKUP($B$3,Base_Clientes!$A:$A,Base_Clientes!$M:$M,"Não encontrado") | C16: =PROCX($B$3;Base_Clientes!$A:$A;Base_Clientes!$M:$M;"Não encontrado")
A17: Buscar valor do plano | B17: =VLOOKUP($B$3,Base_Clientes!$A:$V,10,FALSE) | C17: =PROCV($B$3;Base_Clientes!$A:$V;10;FALSO)
A18: Buscar plano pelo Plano_ID | B18: =XLOOKUP(H2,Base_Planos!$A:$A,Base_Planos!$B:$B,"Não encontrado") | C18: =PROCX(H2;Base_Planos!$A:$A;Base_Planos!$B:$B;"Não encontrado")
A19: Buscar tempo de cliente | B19: =VLOOKUP(B2,Base_Clientes!$A:$V,21,FALSE) | C19: =PROCV(B2;Base_Clientes!$A:$V;21;FALSO)

Sheet Resumo
A1: Resumo do Projeto — Análise de Cancelamento de Clientes (Churn)
A3: Indicador | B3: Resultado | D3: Perguntas para responder no dashboard
A4: Total de clientes | B4: =COUNTA(Base_Clientes!$A$2:$A$1001) -> 1000 | D4: 1 | E4: Quais planos têm maior taxa de cancelamento?
A5: Clientes ativos | B5: =COUNTIF(Base_Clientes!$M$2:$M$1001,"Ativo") -> 708 | D5: 2 | E5: Quais motivos mais aparecem nos cancelamentos?
A6: Clientes cancelados | B6: =COUNTIF(Base_Clientes!$M$2:$M$1001,"Cancelado") -> 292 | D6: 3 | E6: Clientes com baixo uso cancelam mais?
A7: Taxa de churn | B7: =B6/B4 -> 0.292 | D7: 4 | E7: O NPS tem relação com o churn?
A8: Ticket médio | B8: =AVERAGE(Base_Clientes!$X$2:$X$1001) -> 87.45321 | D8: 5 | E8: Qual canal de aquisição traz clientes com maior permanência?
A9: NPS médio | B9: =AVERAGE(Base_Clientes!$R$2:$R$1001) -> 5.106 | D9: 6 | E9: Qual segmento tem maior risco de churn?
A10: Uso médio 30d | B10: =AVERAGE(Base_Clientes!$W$2:$W$1001) -> 54.424 | D10: 7 | E10: Quanto de receita mensal foi perdida com cancelamentos?
